Workbook
Name ClientNameList: OFFSET('Clients List'!$A$2,0,0,COUNTA('Clients List'!$A:$A)-1,1)
Name LessonTypeList: ValidationLists!$A$1:$A$14
Name Package_Semi_Lesson__125: 'Clients List'!$B$6

Sheet Clients List
A1: Client Name | B1: Lesson Type | C1: Package Date | D1: Package Size | E1: Package Balance | F1: Price per Lesson | G1: Email | H1: Phone Number
E2: =IF(OR(D2="",D2=0),"",D2-SUMIFS('Lessons Log'!$E:$E,'Lessons Log'!$C:$C,A2,'Lessons Log'!$D:$D,"*Package*"))
E3: =IF(OR(D3="",D3=0),"",D3-SUMIFS('Lessons Log'!$E:$E,'Lessons Log'!$C:$C,A3,'Lessons Log'!$D:$D,"*Package*"))
E4: =IF(OR(D4="",D4=0),"",D4-SUMIFS('Lessons Log'!$E:$E,'Lessons Log'!$C:$C,A4,'Lessons Log'!$D:$D,"*Package*"))
E5: =IF(OR(D5="",D5=0),"",D5-SUMIFS('Lessons Log'!$E:$E,'Lessons Log'!$C:$C,A5,'Lessons Log'!$D:$D,"*Package*"))
E6: =IF(OR(D6="",D6=0),"",D6-SUMIFS('Lessons Log'!$E:$E,'Lessons Log'!$C:$C,A6,'Lessons Log'!$D:$D,"*Package*"))
E7: =IF(OR(D7="",D7=0),"",D7-SUMIFS('Lessons Log'!$E:$E,'Lessons Log'!$C:$C,A7,'Lessons Log'!$D:$D,"*Package*"))
B8: =IFERROR(INDEX([1]Clients!$D:$D, MATCH(A8, [1]Clients!$A:$A, 0)), "") | E8: =IF(OR(D8="",D8=0),"",D8-SUMIFS('Lessons Log'!$E:$E,'Lessons Log'!$C:$C,A8,'Lessons Log'!$D:$D,"*Package*"))
B9: =IFERROR(INDEX([1]Clients!$D:$D, MATCH(A9, [1]Clients!$A:$A, 0)), "") | E9: =IF(OR(D9="",D9=0),"",D9-SUMIFS('Lessons Log'!$E:$E,'Lessons Log'!$C:$C,A9,'Lessons Log'!$D:$D,"*Package*"))
B10: =IFERROR(INDEX([1]Clients!$D:$D, MATCH(A10, [1]Clients!$A:$A, 0)), "") | E10: =IF(OR(D10="",D10=0),"",D10-SUMIFS('Lessons Log'!$E:$E,'Lessons Log'!$C:$C,A10,'Lessons Log'!$D:$D,"*Package*"))
B11: =IFERROR(INDEX([1]Clients!$D:$D, MATCH(A11, [1]Clients!$A:$A, 0)), "") | E11: =IF(OR(D11="",D11=0),"",D11-SUMIFS('Lessons Log'!$E:$E,'Lessons Log'!$C:$C,A11,'Lessons Log'!$D:$D,"*Package*")) | F11: =IFERROR(INDEX([1]Clients!F:F, MATCH(A11, [1]Clients!A:A, 0)), "")
B12: =IFERROR(INDEX([1]Clients!$D:$D, MATCH(A12, [1]Clients!$A:$A, 0)), "") | E12: =IF(OR(D12="",D12=0),"",D12-SUMIFS('Lessons Log'!$E:$E,'Lessons Log'!$C:$C,A12,'Lessons Log'!$D:$D,"*Package*")) | F12: =IFERROR(INDEX([1]Clients!F:F, MATCH(A12, [1]Clients!A:A, 0)), "")
B13: =IFERROR(INDEX([1]Clients!$D:$D, MATCH(A13, [1]Clients!$A:$A, 0)), "") | E13: =IF(OR(D13="",D13=0),"",D13-SUMIFS('Lessons Log'!$E:$E,'Lessons Log'!$C:$C,A13,'Lessons Log'!$D:$D,"*Package*")) | F13: =IFERROR(INDEX([1]Clients!F:F, MATCH(A13, [1]Clients!A:A, 0)), "")
B14: =IFERROR(INDEX([1]Clients!$D:$D, MATCH(A14, [1]Clients!$A:$A, 0)), "") | E14: =IF(OR(D14="",D14=0),"",D14-SUMIFS('Lessons Log'!$E:$E,'Lessons Log'!$C:$C,A14,'Lessons Log'!$D:$D,"*Package*")) | F14: =IFERROR(INDEX([1]Clients!F:F, MATCH(A14, [1]Clients!A:A, 0)), "")
B15: =IFERROR(INDEX([1]Clients!$D:$D, MATCH(A15, [1]Clients!$A:$A, 0)), "") | E15: =IF(OR(D15="",D15=0),"",D15-SUMIFS('Lessons Log'!$E:$E,'Lessons Log'!$C:$C,A15,'Lessons Log'!$D:$D,"*Package*")) | F15: =IFERROR(INDEX([1]Clients!F:F, MATCH(A15, [1]Clients!A:A, 0)), "")
B16: =IFERROR(INDEX([1]Clients!$D:$D, MATCH(A16, [1]Clients!$A:$A, 0)), "") | E16: =IF(OR(D16="",D16=0),"",D16-SUMIFS('Lessons Log'!$E:$E,'Lessons Log'!$C:$C,A16,'Lessons Log'!$D:$D,"*Package*")) | F16: =IFERROR(INDEX([1]Clients!F:F, MATCH(A16, [1]Clients!A:A, 0)), "")
B17: =IFERROR(INDEX([1]Clients!$D:$D, MATCH(A17, [1]Clients!$A:$A, 0)), "") | E17: =IF(OR(D17="",D17=0),"",D17-SUMIFS('Lessons Log'!$E:$E,'Lessons Log'!$C:$C,A17,'Lessons Log'!$D:$D,"*Package*")) | F17: =IFERROR(INDEX([1]Clients!F:F, MATCH(A17, [1]Clients!A:A, 0)), "")
B18: =IFERROR(INDEX([1]Clients!$D:$D, MATCH(A18, [1]Clients!$A:$A, 0)), "") | E18: =IF(OR(D18="",D18=0),"",D18-SUMIFS('Lessons Log'!$E:$E,'Lessons Log'!$C:$C,A18,'Lessons Log'!$D:$D,"*Package*")) | F18: =IFERROR(INDEX([1]Clients!F:F, MATCH(A18, [1]Clients!A:A, 0)), "")
B19: =IFERROR(INDEX([1]Clients!$D:$D, MATCH(A19, [1]Clients!$A:$A, 0)), "") | E19: =IF(OR(D19="",D19=0),"",D19-SUMIFS('Lessons Log'!$E:$E,'Lessons Log'!$C:$C,A19,'Lessons Log'!$D:$D,"*Package*")) | F19: =IFERROR(INDEX([1]Clients!F:F, MATCH(A19, [1]Clients!A:A, 0)), "")
B20: =IFERROR(INDEX([1]Clients!$D:$D, MATCH(A20, [1]Clients!$A:$A, 0)), "") | E20: =IF(OR(D20="",D20=0),"",D20-SUMIFS('Lessons Log'!$E:$E,'Lessons Log'!$C:$C,A20,'Lessons Log'!$D:$D,"*Package*")) | F20: =IFERROR(INDEX([1]Clients!F:F, MATCH(A20, [1]Clients!A:A, 0)), "")
B21: =IFERROR(INDEX([1]Clients!$D:$D, MATCH(A21, [1]Clients!$A:$A, 0)), "") | E21: =IF(OR(D21="",D21=0),"",D21-SUMIFS('Lessons Log'!$E:$E,'Lessons Log'!$C:$C,A21,'Lessons Log'!$D:$D,"*Package*")) | F21: =IFERROR(INDEX([1]Clients!F:F, MATCH(A21, [1]Clients!A:A, 0)), "")
B22: =IFERROR(INDEX([1]Clients!$D:$D, MATCH(A22, [1]Clients!$A:$A, 0)), "") | E22: =IF(OR(D22="",D22=0),"",D22-SUMIFS('Lessons Log'!$E:$E,'Lessons Log'!$C:$C,A22,'Lessons Log'!$D:$D,"*Package*")) | F22: =IFERROR(INDEX([1]Clients!F:F, MATCH(A22, [1]Clients!A:A, 0)), "")
... B1000: =IFERROR(INDEX([1]Clients!$D:$D, MATCH(A1000, [1]Clients!$A:$A, 0)), "") | E1000: =IF(OR(D1000="",D1000=0),"",D1000-SUMIFS('Lessons Log'!$E:$E,'Lessons Log'!$C:$C,A1000,'Lessons Log'!$D:$D,"*Package*")) | F1000: =IFERROR(INDEX([1]Clients!F:F, MATCH(A1000, [1]Clients!A:A, 0)), "")

Sheet Lessons Log
A1: Date | B1: Payments | C1: Client | D1: Lesson Type | E1: Hours | F1: Package Balance | G1: Session ID | H1: Coach Hours | I1: Rate | J1: Notes
D2: =IFERROR(VLOOKUP(C2,'Clients List'!$A:$F,2,FALSE),"") | F2: =IF(OR(C2="",NOT(ISNUMBER(SEARCH("Package",D2)))),"",VLOOKUP(C2,'Clients List'!$A:$F,4,FALSE)-SUMIFS($E$2:$E2,$C$2:$C2,C2,$D$2:$D2,"*Package*")) | G2: =IF(ISNUMBER(SEARCH("Group",D2)),IFERROR("GRP-"&TEXT(IF(ISNUMBER(A2),A2,DATEVALUE(A2)),"yyyymmdd"),""),"" ) | H2: =IF(ISNUMBER(SEARCH("Group",D2)),IF(G2="",E2,IFERROR(E2/COUNTIF($G2:$G6000,G2),E2)),E2) -> 0 | I2: =IFERROR(VLOOKUP(C2,'Clients List'!A:F,6,FALSE),"")
D3: =IFERROR(VLOOKUP(C3,'Clients List'!$A:$F,2,FALSE),"") | F3: =IF(OR(C3="",NOT(ISNUMBER(SEARCH("Package",D3)))),"",VLOOKUP(C3,'Clients List'!$A:$F,4,FALSE)-SUMIFS($E$2:$E3,$C$2:$C3,C3,$D$2:$D3,"*Package*")) | G3: =IF(ISNUMBER(SEARCH("Group",D3)),IFERROR("GRP-"&TEXT(IF(ISNUMBER(A3),A3,DATEVALUE(A3)),"yyyymmdd"),""),"" ) | H3: =IF(ISNUMBER(SEARCH("Group",D3)),IF(G3="",E3,IFERROR(E3/COUNTIF($G2:$G6000,G3),E3)),E3) -> 0 | I3: =IFERROR(VLOOKUP(C3,'Clients List'!A:F,6,FALSE),"")
D4: =IFERROR(VLOOKUP(C4,'Clients List'!$A:$F,2,FALSE),"") | F4: =IF(OR(C4="",NOT(ISNUMBER(SEARCH("Package",D4)))),"",VLOOKUP(C4,'Clients List'!$A:$F,4,FALSE)-SUMIFS($E$2:$E4,$C$2:$C4,C4,$D$2:$D4,"*Package*")) | G4: =IF(ISNUMBER(SEARCH("Group",D4)),IFERROR("GRP-"&TEXT(IF(ISNUMBER(A4),A4,DATEVALUE(A4)),"yyyymmdd"),""),"" ) | H4: =IF(ISNUMBER(SEARCH("Group",D4)),IF(G4="",E4,IFERROR(E4/COUNTIF($G2:$G6000,G4),E4)),E4) -> 0 | I4: =IFERROR(VLOOKUP(C4,'Clients List'!A:F,6,FALSE),"")
D5: =IFERROR(VLOOKUP(C5,'Clients List'!$A:$F,2,FALSE),"") | F5: =IF(OR(C5="",NOT(ISNUMBER(SEARCH("Package",D5)))),"",VLOOKUP(C5,'Clients List'!$A:$F,4,FALSE)-SUMIFS($E$2:$E5,$C$2:$C5,C5,$D$2:$D5,"*Package*")) | G5: =IF(ISNUMBER(SEARCH("Group",D5)),IFERROR("GRP-"&TEXT(IF(ISNUMBER(A5),A5,DATEVALUE(A5)),"yyyymmdd"),""),"" ) | H5: =IF(ISNUMBER(SEARCH("Group",D5)),IF(G5="",E5,IFERROR(E5/COUNTIF($G2:$G6000,G5),E5)),E5) -> 0 | I5: =IFERROR(VLOOKUP(C5,'Clients List'!A:F,6,FALSE),"")
D6: =IFERROR(VLOOKUP(C6,'Clients List'!$A:$F,2,FALSE),"") | F6: =IF(OR(C6="",NOT(ISNUMBER(SEARCH("Package",D6)))),"",VLOOKUP(C6,'Clients List'!$A:$F,4,FALSE)-SUMIFS($E$2:$E6,$C$2:$C6,C6,$D$2:$D6,"*Package*")) | G6: =IF(ISNUMBER(SEARCH("Group",D6)),IFERROR("GRP-"&TEXT(IF(ISNUMBER(A6),A6,DATEVALUE(A6)),"yyyymmdd"),""),"" ) | H6: =IF(ISNUMBER(SEARCH("Group",D6)),IF(G6="",E6,IFERROR(E6/COUNTIF($G2:$G6000,G6),E6)),E6) -> 0 | I6: =IFERROR(VLOOKUP(C6,'Clients List'!A:F,6,FALSE),"")
D7: =IFERROR(VLOOKUP(C7,'Clients List'!$A:$F,2,FALSE),"") | F7: =IF(OR(C7="",NOT(ISNUMBER(SEARCH("Package",D7)))),"",VLOOKUP(C7,'Clients List'!$A:$F,4,FALSE)-SUMIFS($E$2:$E7,$C$2:$C7,C7,$D$2:$D7,"*Package*")) | G7: =IF(ISNUMBER(SEARCH("Group",D7)),IFERROR("GRP-"&TEXT(IF(ISNUMBER(A7),A7,DATEVALUE(A7)),"yyyymmdd"),""),"" ) | H7: =IF(ISNUMBER(SEARCH("Group",D7)),IF(G7="",E7,IFERROR(E7/COUNTIF($G2:$G6000,G7),E7)),E7) -> 0 | I7: =IFERROR(VLOOKUP(C7,'Clients List'!A:F,6,FALSE),"")
D8: =IFERROR(VLOOKUP(C8,'Clients List'!$A:$F,2,FALSE),"") | F8: =IF(OR(C8="",NOT(ISNUMBER(SEARCH("Package",D8)))),"",VLOOKUP(C8,'Clients List'!$A:$F,4,FALSE)-SUMIFS($E$2:$E8,$C$2:$C8,C8,$D$2:$D8,"*Package*")) | G8: =IF(ISNUMBER(SEARCH("Group",D8)),IFERROR("GRP-"&TEXT(IF(ISNUMBER(A8),A8,DATEVALUE(A8)),"yyyymmdd"),""),"" ) | H8: =IF(ISNUMBER(SEARCH("Group",D8)),IF(G8="",E8,IFERROR(E8/COUNTIF($G2:$G6000,G8),E8)),E8) -> 0 | I8: =IFERROR(VLOOKUP(C8,'Clients List'!A:F,6,FALSE),"")
D9: =IFERROR(VLOOKUP(C9,'Clients List'!$A:$F,2,FALSE),"") | F9: =IF(OR(C9="",NOT(ISNUMBER(SEARCH("Package",D9)))),"",VLOOKUP(C9,'Clients List'!$A:$F,4,FALSE)-SUMIFS($E$2:$E9,$C$2:$C9,C9,$D$2:$D9,"*Package*")) | G9: =IF(ISNUMBER(SEARCH("Group",D9)),IFERROR("GRP-"&TEXT(IF(ISNUMBER(A9),A9,DATEVALUE(A9)),"yyyymmdd"),""),"" ) | H9: =IF(ISNUMBER(SEARCH("Group",D9)),IF(G9="",E9,IFERROR(E9/COUNTIF($G2:$G6000,G9),E9)),E9) -> 0 | I9: =IFERROR(VLOOKUP(C9,'Clients List'!A:F,6,FALSE),"")
D10: =IFERROR(VLOOKUP(C10,'Clients List'!$A:$F,2,FALSE),"") | F10: =IF(OR(C10="",NOT(ISNUMBER(SEARCH("Package",D10)))),"",VLOOKUP(C10,'Clients List'!$A:$F,4,FALSE)-SUMIFS($E$2:$E10,$C$2:$C10,C10,$D$2:$D10,"*Package*")) | G10: =IF(ISNUMBER(SEARCH("Group",D10)),IFERROR("GRP-"&TEXT(IF(ISNUMBER(A10),A10,DATEVALUE(A10)),"yyyymmdd"),""),"" ) | H10: =IF(ISNUMBER(SEARCH("Group",D10)),IF(G10="",E10,IFERROR(E10/COUNTIF($G2:$G6000,G10),E10)),E10) -> 0 | I10: =IFERROR(VLOOKUP(C10,'Clients List'!A:F,6,FALSE),"")
D11: =IFERROR(VLOOKUP(C11,'Clients List'!$A:$F,2,FALSE),"") | F11: =IF(OR(C11="",NOT(ISNUMBER(SEARCH("Package",D11)))),"",VLOOKUP(C11,'Clients List'!$A:$F,4,FALSE)-SUMIFS($E$2:$E11,$C$2:$C11,C11,$D$2:$D11,"*Package*")) | G11: =IF(ISNUMBER(SEARCH("Group",D11)),IFERROR("GRP-"&TEXT(IF(ISNUMBER(A11),A11,DATEVALUE(A11)),"yyyymmdd"),""),"" ) | H11: =IF(ISNUMBER(SEARCH("Group",D11)),IF(G11="",E11,IFERROR(E11/COUNTIF($G2:$G6000,G11),E11)),E11) -> 0 | I11: =IFERROR(VLOOKUP(C11,'Clients List'!A:F,6,FALSE),"")
D12: =IFERROR(VLOOKUP(C12,'Clients List'!$A:$F,2,FALSE),"") | F12: =IF(OR(C12="",NOT(ISNUMBER(SEARCH("Package",D12)))),"",VLOOKUP(C12,'Clients List'!$A:$F,4,FALSE)-SUMIFS($E$2:$E12,$C$2:$C12,C12,$D$2:$D12,"*Package*")) | G12: =IF(ISNUMBER(SEARCH("Group",D12)),IFERROR("GRP-"&TEXT(IF(ISNUMBER(A12),A12,DATEVALUE(A12)),"yyyymmdd"),""),"" ) | H12: =IF(ISNUMBER(SEARCH("Group",D12)),IF(G12="",E12,IFERROR(E12/COUNTIF($G2:$G6000,G12),E12)),E12) -> 0 | I12: =IFERROR(VLOOKUP(C12,'Clients List'!A:F,6,FALSE),"")
D13: =IFERROR(VLOOKUP(C13,'Clients List'!$A:$F,2,FALSE),"") | F13: =IF(OR(C13="",NOT(ISNUMBER(SEARCH("Package",D13)))),"",VLOOKUP(C13,'Clients List'!$A:$F,4,FALSE)-SUMIFS($E$2:$E13,$C$2:$C13,C13,$D$2:$D13,"*Package*")) | G13: =IF(ISNUMBER(SEARCH("Group",D13)),IFERROR("GRP-"&TEXT(IF(ISNUMBER(A13),A13,DATEVALUE(A13)),"yyyymmdd"),""),"" ) | H13: =IF(ISNUMBER(SEARCH("Group",D13)),IF(G13="",E13,IFERROR(E13/COUNTIF($G2:$G6000,G13),E13)),E13) -> 0 | I13: =IFERROR(VLOOKUP(C13,'Clients List'!A:F,6,FALSE),"")
D14: =IFERROR(VLOOKUP(C14,'Clients List'!$A:$F,2,FALSE),"") | F14: =IF(OR(C14="",NOT(ISNUMBER(SEARCH("Package",D14)))),"",VLOOKUP(C14,'Clients List'!$A:$F,4,FALSE)-SUMIFS($E$2:$E14,$C$2:$C14,C14,$D$2:$D14,"*Package*")) | G14: =IF(ISNUMBER(SEARCH("Group",D14)),IFERROR("GRP-"&TEXT(IF(ISNUMBER(A14),A14,DATEVALUE(A14)),"yyyymmdd"),""),"" ) | H14: =IF(ISNUMBER(SEARCH("Group",D14)),IF(G14="",E14,IFERROR(E14/COUNTIF($G2:$G6000,G14),E14)),E14) -> 0 | I14: =IFERROR(VLOOKUP(C14,'Clients List'!A:F,6,FALSE),"")
D15: =IFERROR(VLOOKUP(C15,'Clients List'!$A:$F,2,FALSE),"") | F15: =IF(OR(C15="",NOT(ISNUMBER(SEARCH("Package",D15)))),"",VLOOKUP(C15,'Clients List'!$A:$F,4,FALSE)-SUMIFS($E$2:$E15,$C$2:$C15,C15,$D$2:$D15,"*Package*")) | G15: =IF(ISNUMBER(SEARCH("Group",D15)),IFERROR("GRP-"&TEXT(IF(ISNUMBER(A15),A15,DATEVALUE(A15)),"yyyymmdd"),""),"" ) | H15: =IF(ISNUMBER(SEARCH("Group",D15)),IF(G15="",E15,IFERROR(E15/COUNTIF($G2:$G6000,G15),E15)),E15) -> 0 | I15: =IFERROR(VLOOKUP(C15,'Clients List'!A:F,6,FALSE),"")
D16: =IFERROR(VLOOKUP(C16,'Clients List'!$A:$F,2,FALSE),"") | F16: =IF(OR(C16="",NOT(ISNUMBER(SEARCH("Package",D16)))),"",VLOOKUP(C16,'Clients List'!$A:$F,4,FALSE)-SUMIFS($E$2:$E16,$C$2:$C16,C16,$D$2:$D16,"*Package*")) | G16: =IF(ISNUMBER(SEARCH("Group",D16)),IFERROR("GRP-"&TEXT(IF(ISNUMBER(A16),A16,DATEVALUE(A16)),"yyyymmdd"),""),"" ) | H16: =IF(ISNUMBER(SEARCH("Group",D16)),IF(G16="",E16,IFERROR(E16/COUNTIF($G2:$G6000,G16),E16)),E16) -> 0 | I16: =IFERROR(VLOOKUP(C16,'Clients List'!A:F,6,FALSE),"")
D17: =IFERROR(VLOOKUP(C17,'Clients List'!$A:$F,2,FALSE),"") | F17: =IF(OR(C17="",NOT(ISNUMBER(SEARCH("Package",D17)))),"",VLOOKUP(C17,'Clients List'!$A:$F,4,FALSE)-SUMIFS($E$2:$E17,$C$2:$C17,C17,$D$2:$D17,"*Package*")) | G17: =IF(ISNUMBER(SEARCH("Group",D17)),IFERROR("GRP-"&TEXT(IF(ISNUMBER(A17),A17,DATEVALUE(A17)),"yyyymmdd"),""),"" ) | H17: =IF(ISNUMBER(SEARCH("Group",D17)),IF(G17="",E17,IFERROR(E17/COUNTIF($G2:$G6000,G17),E17)),E17) -> 0 | I17: =IFERROR(VLOOKUP(C17,'Clients List'!A:F,6,FALSE),"")
D18: =IFERROR(VLOOKUP(C18,'Clients List'!$A:$F,2,FALSE),"") | F18: =IF(OR(C18="",NOT(ISNUMBER(SEARCH("Package",D18)))),"",VLOOKUP(C18,'Clients List'!$A:$F,4,FALSE)-SUMIFS($E$2:$E18,$C$2:$C18,C18,$D$2:$D18,"*Package*")) | G18: =IF(ISNUMBER(SEARCH("Group",D18)),IFERROR("GRP-"&TEXT(IF(ISNUMBER(A18),A18,DATEVALUE(A18)),"yyyymmdd"),""),"" ) | H18: =IF(ISNUMBER(SEARCH("Group",D18)),IF(G18="",E18,IFERROR(E18/COUNTIF($G2:$G6000,G18),E18)),E18) -> 0 | I18: =IFERROR(VLOOKUP(C18,'Clients List'!A:F,6,FALSE),"")
D19: =IFERROR(VLOOKUP(C19,'Clients List'!$A:$F,2,FALSE),"") | F19: =IF(OR(C19="",NOT(ISNUMBER(SEARCH("Package",D19)))),"",VLOOKUP(C19,'Clients List'!$A:$F,4,FALSE)-SUMIFS($E$2:$E19,$C$2:$C19,C19,$D$2:$D19,"*Package*")) | G19: =IF(ISNUMBER(SEARCH("Group",D19)),IFERROR("GRP-"&TEXT(IF(ISNUMBER(A19),A19,DATEVALUE(A19)),"yyyymmdd"),""),"" ) | H19: =IF(ISNUMBER(SEARCH("Group",D19)),IF(G19="",E19,IFERROR(E19/COUNTIF($G2:$G6000,G19),E19)),E19) -> 0 | I19: =IFERROR(VLOOKUP(C19,'Clients List'!A:F,6,FALSE),"")
D20: =IFERROR(VLOOKUP(C20,'Clients List'!$A:$F,2,FALSE),"") | F20: =IF(OR(C20="",NOT(ISNUMBER(SEARCH("Package",D20)))),"",VLOOKUP(C20,'Clients List'!$A:$F,4,FALSE)-SUMIFS($E$2:$E20,$C$2:$C20,C20,$D$2:$D20,"*Package*")) | G20: =IF(ISNUMBER(SEARCH("Group",D20)),IFERROR("GRP-"&TEXT(IF(ISNUMBER(A20),A20,DATEVALUE(A20)),"yyyymmdd"),""),"" ) | H20: =IF(ISNUMBER(SEARCH("Group",D20)),IF(G20="",E20,IFERROR(E20/COUNTIF($G2:$G6000,G20),E20)),E20) -> 0 | I20: =IFERROR(VLOOKUP(C20,'Clients List'!A:F,6,FALSE),"")
D21: =IFERROR(VLOOKUP(C21,'Clients List'!$A:$F,2,FALSE),"") | F21: =IF(OR(C21="",NOT(ISNUMBER(SEARCH("Package",D21)))),"",VLOOKUP(C21,'Clients List'!$A:$F,4,FALSE)-SUMIFS($E$2:$E21,$C$2:$C21,C21,$D$2:$D21,"*Package*")) | G21: =IF(ISNUMBER(SEARCH("Group",D21)),IFERROR("GRP-"&TEXT(IF(ISNUMBER(A21),A21,DATEVALUE(A21)),"yyyymmdd"),""),"" ) | H21: =IF(ISNUMBER(SEARCH("Group",D21)),IF(G21="",E21,IFERROR(E21/COUNTIF($G2:$G6000,G21),E21)),E21) -> 0 | I21: =IFERROR(VLOOKUP(C21,'Clients List'!A:F,6,FALSE),"")
D22: =IFERROR(VLOOKUP(C22,'Clients List'!$A:$F,2,FALSE),"") | F22: =IF(OR(C22="",NOT(ISNUMBER(SEARCH("Package",D22)))),"",VLOOKUP(C22,'Clients List'!$A:$F,4,FALSE)-SUMIFS($E$2:$E22,$C$2:$C22,C22,$D$2:$D22,"*Package*")) | G22: =IF(ISNUMBER(SEARCH("Group",D22)),IFERROR("GRP-"&TEXT(IF(ISNUMBER(A22),A22,DATEVALUE(A22)),"yyyymmdd"),""),"" ) | H22: =IF(ISNUMBER(SEARCH("Group",D22)),IF(G22="",E22,IFERROR(E22/COUNTIF($G2:$G6000,G22),E22)),E22) -> 0 | I22: =IFERROR(VLOOKUP(C22,'Clients List'!A:F,6,FALSE),"")
D23: =IFERROR(VLOOKUP(C23,'Clients List'!$A:$F,2,FALSE),"") | F23: =IF(OR(C23="",NOT(ISNUMBER(SEARCH("Package",D23)))),"",VLOOKUP(C23,'Clients List'!$A:$F,4,FALSE)-SUMIFS($E$2:$E23,$C$2:$C23,C23,$D$2:$D23,"*Package*")) | G23: =IF(ISNUMBER(SEARCH("Group",D23)),IFERROR("GRP-"&TEXT(IF(ISNUMBER(A23),A23,DATEVALUE(A23)),"yyyymmdd"),""),"" ) | H23: =IF(ISNUMBER(SEARCH("Group",D23)),IF(G23="",E23,IFERROR(E23/COUNTIF($G2:$G6000,G23),E23)),E23) -> 0 | I23: =IFERROR(VLOOKUP(C23,'Clients List'!A:F,6,FALSE),"")
D24: =IFERROR(VLOOKUP(C24,'Clients List'!$A:$F,2,FALSE),"") | F24: =IF(OR(C24="",NOT(ISNUMBER(SEARCH("Package",D24)))),"",VLOOKUP(C24,'Clients List'!$A:$F,4,FALSE)-SUMIFS($E$2:$E24,$C$2:$C24,C24,$D$2:$D24,"*Package*")) | G24: =IF(ISNUMBER(SEARCH("Group",D24)),IFERROR("GRP-"&TEXT(IF(ISNUMBER(A24),A24,DATEVALUE(A24)),"yyyymmdd"),""),"" ) | H24: =IF(ISNUMBER(SEARCH("Group",D24)),IF(G24="",E24,IFERROR(E24/COUNTIF($G2:$G6000,G24),E24)),E24) -> 0 | I24: =IFERROR(VLOOKUP(C24,'Clients List'!A:F,6,FALSE),"")
D25: =IFERROR(VLOOKUP(C25,'Clients List'!$A:$F,2,FALSE),"") | F25: =IF(OR(C25="",NOT(ISNUMBER(SEARCH("Package",D25)))),"",VLOOKUP(C25,'Clients List'!$A:$F,4,FALSE)-SUMIFS($E$2:$E25,$C$2:$C25,C25,$D$2:$D25,"*Package*")) | G25: =IF(ISNUMBER(SEARCH("Group",D25)),IFERROR("GRP-"&TEXT(IF(ISNUMBER(A25),A25,DATEVALUE(A25)),"yyyymmdd"),""),"" ) | H25: =IF(ISNUMBER(SEARCH("Group",D25)),IF(G25="",E25,IFERROR(E25/COUNTIF($G2:$G6000,G25),E25)),E25) -> 0 | I25: =IFERROR(VLOOKUP(C25,'Clients List'!A:F,6,FALSE),"")
D26: =IFERROR(VLOOKUP(C26,'Clients List'!$A:$F,2,FALSE),"") | F26: =IF(OR(C26="",NOT(ISNUMBER(SEARCH("Package",D26)))),"",VLOOKUP(C26,'Clients List'!$A:$F,4,FALSE)-SUMIFS($E$2:$E26,$C$2:$C26,C26,$D$2:$D26,"*Package*")) | G26: =IF(ISNUMBER(SEARCH("Group",D26)),IFERROR("GRP-"&TEXT(IF(ISNUMBER(A26),A26,DATEVALUE(A26)),"yyyymmdd"),""),"" ) | H26: =IF(ISNUMBER(SEARCH("Group",D26)),IF(G26="",E26,IFERROR(E26/COUNTIF($G2:$G6000,G26),E26)),E26) -> 0 | I26: =IFERROR(VLOOKUP(C26,'Clients List'!A:F,6,FALSE),"")
D27: =IFERROR(VLOOKUP(C27,'Clients List'!$A:$F,2,FALSE),"") | F27: =IF(OR(C27="",NOT(ISNUMBER(SEARCH("Package",D27)))),"",VLOOKUP(C27,'Clients List'!$A:$F,4,FALSE)-SUMIFS($E$2:$E27,$C$2:$C27,C27,$D$2:$D27,"*Package*")) | G27: =IF(ISNUMBER(SEARCH("Group",D27)),IFERROR("GRP-"&TEXT(IF(ISNUMBER(A27),A27,DATEVALUE(A27)),"yyyymmdd"),""),"" ) | H27: =IF(ISNUMBER(SEARCH("Group",D27)),IF(G27="",E27,IFERROR(E27/COUNTIF($G2:$G6000,G27),E27)),E27) -> 0 | I27: =IFERROR(VLOOKUP(C27,'Clients List'!A:F,6,FALSE),"")
D28: =IFERROR(VLOOKUP(C28,'Clients List'!$A:$F,2,FALSE),"") | F28: =IF(OR(C28="",NOT(ISNUMBER(SEARCH("Package",D28)))),"",VLOOKUP(C28,'Clients List'!$A:$F,4,FALSE)-SUMIFS($E$2:$E28,$C$2:$C28,C28,$D$2:$D28,"*Package*")) | G28: =IF(ISNUMBER(SEARCH("Group",D28)),IFERROR("GRP-"&TEXT(IF(ISNUMBER(A28),A28,DATEVALUE(A28)),"yyyymmdd"),""),"" ) | H28: =IF(ISNUMBER(SEARCH("Group",D28)),IF(G28="",E28,IFERROR(E28/COUNTIF($G2:$G6000,G28),E28)),E28) -> 0 | I28: =IFERROR(VLOOKUP(C28,'Clients List'!A:F,6,FALSE),"")
D29: =IFERROR(VLOOKUP(C29,'Clients List'!$A:$F,2,FALSE),"") | F29: =IF(OR(C29="",NOT(ISNUMBER(SEARCH("Package",D29)))),"",VLOOKUP(C29,'Clients List'!$A:$F,4,FALSE)-SUMIFS($E$2:$E29,$C$2:$C29,C29,$D$2:$D29,"*Package*")) | G29: =IF(ISNUMBER(SEARCH("Group",D29)),IFERROR("GRP-"&TEXT(IF(ISNUMBER(A29),A29,DATEVALUE(A29)),"yyyymmdd"),""),"" ) | H29: =IF(ISNUMBER(SEARCH("Group",D29)),IF(G29="",E29,IFERROR(E29/COUNTIF($G2:$G6000,G29),E29)),E29) -> 0 | I29: =IFERROR(VLOOKUP(C29,'Clients List'!A:F,6,FALSE),"")
D30: =IFERROR(VLOOKUP(C30,'Clients List'!$A:$F,2,FALSE),"") | F30: =IF(OR(C30="",NOT(ISNUMBER(SEARCH("Package",D30)))),"",VLOOKUP(C30,'Clients List'!$A:$F,4,FALSE)-SUMIFS($E$2:$E30,$C$2:$C30,C30,$D$2:$D30,"*Package*")) | G30: =IF(ISNUMBER(SEARCH("Group",D30)),IFERROR("GRP-"&TEXT(IF(ISNUMBER(A30),A30,DATEVALUE(A30)),"yyyymmdd"),""),"" ) | H30: =IF(ISNUMBER(SEARCH("Group",D30)),IF(G30="",E30,IFERROR(E30/COUNTIF($G2:$G6000,G30),E30)),E30) -> 0 | I30: =IFERROR(VLOOKUP(C30,'Clients List'!A:F,6,FALSE),"")
D31: =IFERROR(VLOOKUP(C31,'Clients List'!$A:$F,2,FALSE),"") | F31: =IF(OR(C31="",NOT(ISNUMBER(SEARCH("Package",D31)))),"",VLOOKUP(C31,'Clients List'!$A:$F,4,FALSE)-SUMIFS($E$2:$E31,$C$2:$C31,C31,$D$2:$D31,"*Package*")) | G31: =IF(ISNUMBER(SEARCH("Group",D31)),IFERROR("GRP-"&TEXT(IF(ISNUMBER(A31),A31,DATEVALUE(A31)),"yyyymmdd"),""),"" ) | H31: =IF(ISNUMBER(SEARCH("Group",D31)),IF(G31="",E31,IFERROR(E31/COUNTIF($G2:$G6000,G31),E31)),E31) -> 0 | I31: =IFERROR(VLOOKUP(C31,'Clients List'!A:F,6,FALSE),"")
D32: =IFERROR(VLOOKUP(C32,'Clients List'!$A:$F,2,FALSE),"") | F32: =IF(OR(C32="",NOT(ISNUMBER(SEARCH("Package",D32)))),"",VLOOKUP(C32,'Clients List'!$A:$F,4,FALSE)-SUMIFS($E$2:$E32,$C$2:$C32,C32,$D$2:$D32,"*Package*")) | G32: =IF(ISNUMBER(SEARCH("Group",D32)),IFERROR("GRP-"&TEXT(IF(ISNUMBER(A32),A32,DATEVALUE(A32)),"yyyymmdd"),""),"" ) | H32: =IF(ISNUMBER(SEARCH("Group",D32)),IF(G32="",E32,IFERROR(E32/COUNTIF($G2:$G6000,G32),E32)),E32) -> 0 | I32: =IFERROR(VLOOKUP(C32,'Clients List'!A:F,6,FALSE),"")
D33: =IFERROR(VLOOKUP(C33,'Clients List'!$A:$F,2,FALSE),"") | F33: =IF(OR(C33="",NOT(ISNUMBER(SEARCH("Package",D33)))),"",VLOOKUP(C33,'Clients List'!$A:$F,4,FALSE)-SUMIFS($E$2:$E33,$C$2:$C33,C33,$D$2:$D33,"*Package*")) | G33: =IF(ISNUMBER(SEARCH("Group",D33)),IFERROR("GRP-"&TEXT(IF(ISNUMBER(A33),A33,DATEVALUE(A33)),"yyyymmdd"),""),"" ) | H33: =IF(ISNUMBER(SEARCH("Group",D33)),IF(G33="",E33,IFERROR(E33/COUNTIF($G2:$G6000,G33),E33)),E33) -> 0 | I33: =IFERROR(VLOOKUP(C33,'Clients List'!A:F,6,FALSE),"")
D34: =IFERROR(VLOOKUP(C34,'Clients List'!$A:$F,2,FALSE),"") | F34: =IF(OR(C34="",NOT(ISNUMBER(SEARCH("Package",D34)))),"",VLOOKUP(C34,'Clients List'!$A:$F,4,FALSE)-SUMIFS($E$2:$E34,$C$2:$C34,C34,$D$2:$D34,"*Package*")) | G34: =IF(ISNUMBER(SEARCH("Group",D34)),IFERROR("GRP-"&TEXT(IF(ISNUMBER(A34),A34,DATEVALUE(A34)),"yyyymmdd"),""),"" ) | H34: =IF(ISNUMBER(SEARCH("Group",D34)),IF(G34="",E34,IFERROR(E34/COUNTIF($G2:$G6000,G34),E34)),E34) -> 0 | I34: =IFERROR(VLOOKUP(C34,'Clients List'!A:F,6,FALSE),"")
D35: =IFERROR(VLOOKUP(C35,'Clients List'!$A:$F,2,FALSE),"") | F35: =IF(OR(C35="",NOT(ISNUMBER(SEARCH("Package",D35)))),"",VLOOKUP(C35,'Clients List'!$A:$F,4,FALSE)-SUMIFS($E$2:$E35,$C$2:$C35,C35,$D$2:$D35,"*Package*")) | G35: =IF(ISNUMBER(SEARCH("Group",D35)),IFERROR("GRP-"&TEXT(IF(ISNUMBER(A35),A35,DATEVALUE(A35)),"yyyymmdd"),""),"" ) | H35: =IF(ISNUMBER(SEARCH("Group",D35)),IF(G35="",E35,IFERROR(E35/COUNTIF($G2:$G6000,G35),E35)),E35) -> 0 | I35: =IFERROR(VLOOKUP(C35,'Clients List'!A:F,6,FALSE),"")
D36: =IFERROR(VLOOKUP(C36,'Clients List'!$A:$F,2,FALSE),"") | F36: =IF(OR(C36="",NOT(ISNUMBER(SEARCH("Package",D36)))),"",VLOOKUP(C36,'Clients List'!$A:$F,4,FALSE)-SUMIFS($E$2:$E36,$C$2:$C36,C36,$D$2:$D36,"*Package*")) | G36: =IF(ISNUMBER(SEARCH("Group",D36)),IFERROR("GRP-"&TEXT(IF(ISNUMBER(A36),A36,DATEVALUE(A36)),"yyyymmdd"),""),"" ) | H36: =IF(ISNUMBER(SEARCH("Group",D36)),IF(G36="",E36,IFERROR(E36/COUNTIF($G2:$G6000,G36),E36)),E36) -> 0 | I36: =IFERROR(VLOOKUP(C36,'Clients List'!A:F,6,FALSE),"")
D37: =IFERROR(VLOOKUP(C37,'Clients List'!$A:$F,2,FALSE),"") | F37: =IF(OR(C37="",NOT(ISNUMBER(SEARCH("Package",D37)))),"",VLOOKUP(C37,'Clients List'!$A:$F,4,FALSE)-SUMIFS($E$2:$E37,$C$2:$C37,C37,$D$2:$D37,"*Package*")) | G37: =IF(ISNUMBER(SEARCH("Group",D37)),IFERROR("GRP-"&TEXT(IF(ISNUMBER(A37),A37,DATEVALUE(A37)),"yyyymmdd"),""),"" ) | H37: =IF(ISNUMBER(SEARCH("Group",D37)),IF(G37="",E37,IFERROR(E37/COUNTIF($G2:$G6000,G37),E37)),E37) -> 0 | I37: =IFERROR(VLOOKUP(C37,'Clients List'!A:F,6,FALSE),"")
D38: =IFERROR(VLOOKUP(C38,'Clients List'!$A:$F,2,FALSE),"") | F38: =IF(OR(C38="",NOT(ISNUMBER(SEARCH("Package",D38)))),"",VLOOKUP(C38,'Clients List'!$A:$F,4,FALSE)-SUMIFS($E$2:$E38,$C$2:$C38,C38,$D$2:$D38,"*Package*")) | G38: =IF(ISNUMBER(SEARCH("Group",D38)),IFERROR("GRP-"&TEXT(IF(ISNUMBER(A38),A38,DATEVALUE(A38)),"yyyymmdd"),""),"" ) | H38: =IF(ISNUMBER(SEARCH("Group",D38)),IF(G38="",E38,IFERROR(E38/COUNTIF($G2:$G6000,G38),E38)),E38) -> 0 | I38: =IFERROR(VLOOKUP(C38,'Clients List'!A:F,6,FALSE),"")
D39: =IFERROR(VLOOKUP(C39,'Clients List'!$A:$F,2,FALSE),"") | F39: =IF(OR(C39="",NOT(ISNUMBER(SEARCH("Package",D39)))),"",VLOOKUP(C39,'Clients List'!$A:$F,4,FALSE)-SUMIFS($E$2:$E39,$C$2:$C39,C39,$D$2:$D39,"*Package*")) | G39: =IF(ISNUMBER(SEARCH("Group",D39)),IFERROR("GRP-"&TEXT(IF(ISNUMBER(A39),A39,DATEVALUE(A39)),"yyyymmdd"),""),"" ) | H39: =IF(ISNUMBER(SEARCH("Group",D39)),IF(G39="",E39,IFERROR(E39/COUNTIF($G2:$G6000,G39),E39)),E39) -> 0 | I39: =IFERROR(VLOOKUP(C39,'Clients List'!A:F,6,FALSE),"")
D40: =IFERROR(VLOOKUP(C40,'Clients List'!$A:$F,2,FALSE),"") | F40: =IF(OR(C40="",NOT(ISNUMBER(SEARCH("Package",D40)))),"",VLOOKUP(C40,'Clients List'!$A:$F,4,FALSE)-SUMIFS($E$2:$E40,$C$2:$C40,C40,$D$2:$D40,"*Package*")) | G40: =IF(ISNUMBER(SEARCH("Group",D40)),IFERROR("GRP-"&TEXT(IF(ISNUMBER(A40),A40,DATEVALUE(A40)),"yyyymmdd"),""),"" ) | H40: =IF(ISNUMBER(SEARCH("Group",D40)),IF(G40="",E40,IFERROR(E40/COUNTIF($G2:$G6000,G40),E40)),E40) -> 0 | I40: =IFERROR(VLOOKUP(C40,'Clients List'!A:F,6,FALSE),"")
D41: =IFERROR(VLOOKUP(C41,'Clients List'!$A:$F,2,FALSE),"") | F41: =IF(OR(C41="",NOT(ISNUMBER(SEARCH("Package",D41)))),"",VLOOKUP(C41,'Clients List'!$A:$F,4,FALSE)-SUMIFS($E$2:$E41,$C$2:$C41,C41,$D$2:$D41,"*Package*")) | G41: =IF(ISNUMBER(SEARCH("Group",D41)),IFERROR("GRP-"&TEXT(IF(ISNUMBER(A41),A41,DATEVALUE(A41)),"yyyymmdd"),""),"" ) | H41: =IF(ISNUMBER(SEARCH("Group",D41)),IF(G41="",E41,IFERROR(E41/COUNTIF($G2:$G6000,G41),E41)),E41) -> 0 | I41: =IFERROR(VLOOKUP(C41,'Clients List'!A:F,6,FALSE),"")
D42: =IFERROR(VLOOKUP(C42,'Clients List'!$A:$F,2,FALSE),"") | F42: =IF(OR(C42="",NOT(ISNUMBER(SEARCH("Package",D42)))),"",VLOOKUP(C42,'Clients List'!$A:$F,4,FALSE)-SUMIFS($E$2:$E42,$C$2:$C42,C42,$D$2:$D42,"*Package*")) | G42: =IF(ISNUMBER(SEARCH("Group",D42)),IFERROR("GRP-"&TEXT(IF(ISNUMBER(A42),A42,DATEVALUE(A42)),"yyyymmdd"),""),"" ) | H42: =IF(ISNUMBER(SEARCH("Group",D42)),IF(G42="",E42,IFERROR(E42/COUNTIF($G2:$G6000,G42),E42)),E42) -> 0 | I42: =IFERROR(VLOOKUP(C42,'Clients List'!A:F,6,FALSE),"")
D43: =IFERROR(VLOOKUP(C43,'Clients List'!$A:$F,2,FALSE),"") | F43: =IF(OR(C43="",NOT(ISNUMBER(SEARCH("Package",D43)))),"",VLOOKUP(C43,'Clients List'!$A:$F,4,FALSE)-SUMIFS($E$2:$E43,$C$2:$C43,C43,$D$2:$D43,"*Package*")) | G43: =IF(ISNUMBER(SEARCH("Group",D43)),IFERROR("GRP-"&TEXT(IF(ISNUMBER(A43),A43,DATEVALUE(A43)),"yyyymmdd"),""),"" ) | H43: =IF(ISNUMBER(SEARCH("Group",D43)),IF(G43="",E43,IFERROR(E43/COUNTIF($G2:$G6000,G43),E43)),E43) -> 0 | I43: =IFERROR(VLOOKUP(C43,'Clients List'!A:F,6,FALSE),"")
D44: =IFERROR(VLOOKUP(C44,'Clients List'!$A:$F,2,FALSE),"") | F44: =IF(OR(C44="",NOT(ISNUMBER(SEARCH("Package",D44)))),"",VLOOKUP(C44,'Clients List'!$A:$F,4,FALSE)-SUMIFS($E$2:$E44,$C$2:$C44,C44,$D$2:$D44,"*Package*")) | G44: =IF(ISNUMBER(SEARCH("Group",D44)),IFERROR("GRP-"&TEXT(IF(ISNUMBER(A44),A44,DATEVALUE(A44)),"yyyymmdd"),""),"" ) | H44: =IF(ISNUMBER(SEARCH("Group",D44)),IF(G44="",E44,IFERROR(E44/COUNTIF($G2:$G6000,G44),E44)),E44) -> 0 | I44: =IFERROR(VLOOKUP(C44,'Clients List'!A:F,6,FALSE),"")
D45: =IFERROR(VLOOKUP(C45,'Clients List'!$A:$F,2,FALSE),"") | F45: =IF(OR(C45="",NOT(ISNUMBER(SEARCH("Package",D45)))),"",VLOOKUP(C45,'Clients List'!$A:$F,4,FALSE)-SUMIFS($E$2:$E45,$C$2:$C45,C45,$D$2:$D45,"*Package*")) | G45: =IF(ISNUMBER(SEARCH("Group",D45)),IFERROR("GRP-"&TEXT(IF(ISNUMBER(A45),A45,DATEVALUE(A45)),"yyyymmdd"),""),"" ) | H45: =IF(ISNUMBER(SEARCH("Group",D45)),IF(G45="",E45,IFERROR(E45/COUNTIF($G2:$G6000,G45),E45)),E45) -> 0 | I45: =IFERROR(VLOOKUP(C45,'Clients List'!A:F,6,FALSE),"")
D46: =IFERROR(VLOOKUP(C46,'Clients List'!$A:$F,2,FALSE),"") | F46: =IF(OR(C46="",NOT(ISNUMBER(SEARCH("Package",D46)))),"",VLOOKUP(C46,'Clients List'!$A:$F,4,FALSE)-SUMIFS($E$2:$E46,$C$2:$C46,C46,$D$2:$D46,"*Package*")) | G46: =IF(ISNUMBER(SEARCH("Group",D46)),IFERROR("GRP-"&TEXT(IF(ISNUMBER(A46),A46,DATEVALUE(A46)),"yyyymmdd"),""),"" ) | H46: =IF(ISNUMBER(SEARCH("Group",D46)),IF(G46="",E46,IFERROR(E46/COUNTIF($G2:$G6000,G46),E46)),E46) -> 0 | I46: =IFERROR(VLOOKUP(C46,'Clients List'!A:F,6,FALSE),"")
D47: =IFERROR(VLOOKUP(C47,'Clients List'!$A:$F,2,FALSE),"") | F47: =IF(OR(C47="",NOT(ISNUMBER(SEARCH("Package",D47)))),"",VLOOKUP(C47,'Clients List'!$A:$F,4,FALSE)-SUMIFS($E$2:$E47,$C$2:$C47,C47,$D$2:$D47,"*Package*")) | G47: =IF(ISNUMBER(SEARCH("Group",D47)),IFERROR("GRP-"&TEXT(IF(ISNUMBER(A47),A47,DATEVALUE(A47)),"yyyymmdd"),""),"" ) | H47: =IF(ISNUMBER(SEARCH("Group",D47)),IF(G47="",E47,IFERROR(E47/COUNTIF($G2:$G6000,G47),E47)),E47) -> 0 | I47: =IFERROR(VLOOKUP(C47,'Clients List'!A:F,6,FALSE),"")
D48: =IFERROR(VLOOKUP(C48,'Clients List'!$A:$F,2,FALSE),"") | F48: =IF(OR(C48="",NOT(ISNUMBER(SEARCH("Package",D48)))),"",VLOOKUP(C48,'Clients List'!$A:$F,4,FALSE)-SUMIFS($E$2:$E48,$C$2:$C48,C48,$D$2:$D48,"*Package*")) | G48: =IF(ISNUMBER(SEARCH("Group",D48)),IFERROR("GRP-"&TEXT(IF(ISNUMBER(A48),A48,DATEVALUE(A48)),"yyyymmdd"),""),"" ) | H48: =IF(ISNUMBER(SEARCH("Group",D48)),IF(G48="",E48,IFERROR(E48/COUNTIF($G2:$G6000,G48),E48)),E48) -> 0 | I48: =IFERROR(VLOOKUP(C48,'Clients List'!A:F,6,FALSE),"")
D49: =IFERROR(VLOOKUP(C49,'Clients List'!$A:$F,2,FALSE),"") | F49: =IF(OR(C49="",NOT(ISNUMBER(SEARCH("Package",D49)))),"",VLOOKUP(C49,'Clients List'!$A:$F,4,FALSE)-SUMIFS($E$2:$E49,$C$2:$C49,C49,$D$2:$D49,"*Package*")) | G49: =IF(ISNUMBER(SEARCH("Group",D49)),IFERROR("GRP-"&TEXT(IF(ISNUMBER(A49),A49,DATEVALUE(A49)),"yyyymmdd"),""),"" ) | H49: =IF(ISNUMBER(SEARCH("Group",D49)),IF(G49="",E49,IFERROR(E49/COUNTIF($G2:$G6000,G49),E49)),E49) -> 0 | I49: =IFERROR(VLOOKUP(C49,'Clients List'!A:F,6,FALSE),"")
D50: =IFERROR(VLOOKUP(C50,'Clients List'!$A:$F,2,FALSE),"") | F50: =IF(OR(C50="",NOT(ISNUMBER(SEARCH("Package",D50)))),"",VLOOKUP(C50,'Clients List'!$A:$F,4,FALSE)-SUMIFS($E$2:$E50,$C$2:$C50,C50,$D$2:$D50,"*Package*")) | G50: =IF(ISNUMBER(SEARCH("Group",D50)),IFERROR("GRP-"&TEXT(IF(ISNUMBER(A50),A50,DATEVALUE(A50)),"yyyymmdd"),""),"" ) | H50: =IF(ISNUMBER(SEARCH("Group",D50)),IF(G50="",E50,IFERROR(E50/COUNTIF($G2:$G6000,G50),E50)),E50) -> 0 | I50: =IFERROR(VLOOKUP(C50,'Clients List'!A:F,6,FALSE),"")
D51: =IFERROR(VLOOKUP(C51,'Clients List'!$A:$F,2,FALSE),"") | F51: =IF(OR(C51="",NOT(ISNUMBER(SEARCH("Package",D51)))),"",VLOOKUP(C51,'Clients List'!$A:$F,4,FALSE)-SUMIFS($E$2:$E51,$C$2:$C51,C51,$D$2:$D51,"*Package*")) | G51: =IF(ISNUMBER(SEARCH("Group",D51)),IFERROR("GRP-"&TEXT(IF(ISNUMBER(A51),A51,DATEVALUE(A51)),"yyyymmdd"),""),"" ) | H51: =IF(ISNUMBER(SEARCH("Group",D51)),IF(G51="",E51,IFERROR(E51/COUNTIF($G2:$G6000,G51),E51)),E51) -> 0 | I51: =IFERROR(VLOOKUP(C51,'Clients List'!A:F,6,FALSE),"")
D52: =IFERROR(VLOOKUP(C52,'Clients List'!$A:$F,2,FALSE),"") | F52: =IF(OR(C52="",NOT(ISNUMBER(SEARCH("Package",D52)))),"",VLOOKUP(C52,'Clients List'!$A:$F,4,FALSE)-SUMIFS($E$2:$E52,$C$2:$C52,C52,$D$2:$D52,"*Package*")) | G52: =IF(ISNUMBER(SEARCH("Group",D52)),IFERROR("GRP-"&TEXT(IF(ISNUMBER(A52),A52,DATEVALUE(A52)),"yyyymmdd"),""),"" ) | H52: =IF(ISNUMBER(SEARCH("Group",D52)),IF(G52="",E52,IFERROR(E52/COUNTIF($G2:$G6000,G52),E52)),E52) -> 0 | I52: =IFERROR(VLOOKUP(C52,'Clients List'!A:F,6,FALSE),"")
D53: =IFERROR(VLOOKUP(C53,'Clients List'!$A:$F,2,FALSE),"") | F53: =IF(OR(C53="",NOT(ISNUMBER(SEARCH("Package",D53)))),"",VLOOKUP(C53,'Clients List'!$A:$F,4,FALSE)-SUMIFS($E$2:$E53,$C$2:$C53,C53,$D$2:$D53,"*Package*")) | G53: =IF(ISNUMBER(SEARCH("Group",D53)),IFERROR("GRP-"&TEXT(IF(ISNUMBER(A53),A53,DATEVALUE(A53)),"yyyymmdd"),""),"" ) | H53: =IF(ISNUMBER(SEARCH("Group",D53)),IF(G53="",E53,IFERROR(E53/COUNTIF($G2:$G6000,G53),E53)),E53) -> 0 | I53: =IFERROR(VLOOKUP(C53,'Clients List'!A:F,6,FALSE),"")
D54: =IFERROR(VLOOKUP(C54,'Clients List'!$A:$F,2,FALSE),"") | F54: =IF(OR(C54="",NOT(ISNUMBER(SEARCH("Package",D54)))),"",VLOOKUP(C54,'Clients List'!$A:$F,4,FALSE)-SUMIFS($E$2:$E54,$C$2:$C54,C54,$D$2:$D54,"*Package*")) | G54: =IF(ISNUMBER(SEARCH("Group",D54)),IFERROR("GRP-"&TEXT(IF(ISNUMBER(A54),A54,DATEVALUE(A54)),"yyyymmdd"),""),"" ) | H54: =IF(ISNUMBER(SEARCH("Group",D54)),IF(G54="",E54,IFERROR(E54/COUNTIF($G2:$G6000,G54),E54)),E54) -> 0 | I54: =IFERROR(VLOOKUP(C54,'Clients List'!A:F,6,FALSE),"")
D55: =IFERROR(VLOOKUP(C55,'Clients List'!$A:$F,2,FALSE),"") | F55: =IF(OR(C55="",NOT(ISNUMBER(SEARCH("Package",D55)))),"",VLOOKUP(C55,'Clients List'!$A:$F,4,FALSE)-SUMIFS($E$2:$E55,$C$2:$C55,C55,$D$2:$D55,"*Package*")) | G55: =IF(ISNUMBER(SEARCH("Group",D55)),IFERROR("GRP-"&TEXT(IF(ISNUMBER(A55),A55,DATEVALUE(A55)),"yyyymmdd"),""),"" ) | H55: =IF(ISNUMBER(SEARCH("Group",D55)),IF(G55="",E55,IFERROR(E55/COUNTIF($G2:$G6000,G55),E55)),E55) -> 0 | I55: =IFERROR(VLOOKUP(C55,'Clients List'!A:F,6,FALSE),"")
D56: =IFERROR(VLOOKUP(C56,'Clients List'!$A:$F,2,FALSE),"") | F56: =IF(OR(C56="",NOT(ISNUMBER(SEARCH("Package",D56)))),"",VLOOKUP(C56,'Clients List'!$A:$F,4,FALSE)-SUMIFS($E$2:$E56,$C$2:$C56,C56,$D$2:$D56,"*Package*")) | G56: =IF(ISNUMBER(SEARCH("Group",D56)),IFERROR("GRP-"&TEXT(IF(ISNUMBER(A56),A56,DATEVALUE(A56)),"yyyymmdd"),""),"" ) | H56: =IF(ISNUMBER(SEARCH("Group",D56)),IF(G56="",E56,IFERROR(E56/COUNTIF($G2:$G6000,G56),E56)),E56) -> 0 | I56: =IFERROR(VLOOKUP(C56,'Clients List'!A:F,6,FALSE),"")
D57: =IFERROR(VLOOKUP(C57,'Clients List'!$A:$F,2,FALSE),"") | F57: =IF(OR(C57="",NOT(ISNUMBER(SEARCH("Package",D57)))),"",VLOOKUP(C57,'Clients List'!$A:$F,4,FALSE)-SUMIFS($E$2:$E57,$C$2:$C57,C57,$D$2:$D57,"*Package*")) | G57: =IF(ISNUMBER(SEARCH("Group",D57)),IFERROR("GRP-"&TEXT(IF(ISNUMBER(A57),A57,DATEVALUE(A57)),"yyyymmdd"),""),"" ) | H57: =IF(ISNUMBER(SEARCH("Group",D57)),IF(G57="",E57,IFERROR(E57/COUNTIF($G2:$G6000,G57),E57)),E57) -> 0 | I57: =IFERROR(VLOOKUP(C57,'Clients List'!A:F,6,FALSE),"")
D58: =IFERROR(VLOOKUP(C58,'Clients List'!$A:$F,2,FALSE),"") | F58: =IF(OR(C58="",NOT(ISNUMBER(SEARCH("Package",D58)))),"",VLOOKUP(C58,'Clients List'!$A:$F,4,FALSE)-SUMIFS($E$2:$E58,$C$2:$C58,C58,$D$2:$D58,"*Package*")) | G58: =IF(ISNUMBER(SEARCH("Group",D58)),IFERROR("GRP-"&TEXT(IF(ISNUMBER(A58),A58,DATEVALUE(A58)),"yyyymmdd"),""),"" ) | H58: =IF(ISNUMBER(SEARCH("Group",D58)),IF(G58="",E58,IFERROR(E58/COUNTIF($G2:$G6000,G58),E58)),E58) -> 0 | I58: =IFERROR(VLOOKUP(C58,'Clients List'!A:F,6,FALSE),"")
D59: =IFERROR(VLOOKUP(C59,'Clients List'!$A:$F,2,FALSE),"") | F59: =IF(OR(C59="",NOT(ISNUMBER(SEARCH("Package",D59)))),"",VLOOKUP(C59,'Clients List'!$A:$F,4,FALSE)-SUMIFS($E$2:$E59,$C$2:$C59,C59,$D$2:$D59,"*Package*")) | G59: =IF(ISNUMBER(SEARCH("Group",D59)),IFERROR("GRP-"&TEXT(IF(ISNUMBER(A59),A59,DATEVALUE(A59)),"yyyymmdd"),""),"" ) | H59: =IF(ISNUMBER(SEARCH("Group",D59)),IF(G59="",E59,IFERROR(E59/COUNTIF($G2:$G6000,G59),E59)),E59) -> 0 | I59: =IFERROR(VLOOKUP(C59,'Clients List'!A:F,6,FALSE),"")
D60: =IFERROR(VLOOKUP(C60,'Clients List'!$A:$F,2,FALSE),"") | F60: =IF(OR(C60="",NOT(ISNUMBER(SEARCH("Package",D60)))),"",VLOOKUP(C60,'Clients List'!$A:$F,4,FALSE)-SUMIFS($E$2:$E60,$C$2:$C60,C60,$D$2:$D60,"*Package*")) | G60: =IF(ISNUMBER(SEARCH("Group",D60)),IFERROR("GRP-"&TEXT(IF(ISNUMBER(A60),A60,DATEVALUE(A60)),"yyyymmdd"),""),"" ) | H60: =IF(ISNUMBER(SEARCH("Group",D60)),IF(G60="",E60,IFERROR(E60/COUNTIF($G2:$G6000,G60),E60)),E60) -> 0 | I60: =IFERROR(VLOOKUP(C60,'Clients List'!A:F,6,FALSE),"")
D61: =IFERROR(VLOOKUP(C61,'Clients List'!$A:$F,2,FALSE),"") | F61: =IF(OR(C61="",NOT(ISNUMBER(SEARCH("Package",D61)))),"",VLOOKUP(C61,'Clients List'!$A:$F,4,FALSE)-SUMIFS($E$2:$E61,$C$2:$C61,C61,$D$2:$D61,"*Package*")) | G61: =IF(ISNUMBER(SEARCH("Group",D61)),IFERROR("GRP-"&TEXT(IF(ISNUMBER(A61),A61,DATEVALUE(A61)),"yyyymmdd"),""),"" ) | H61: =IF(ISNUMBER(SEARCH("Group",D61)),IF(G61="",E61,IFERROR(E61/COUNTIF($G2:$G6000,G61),E61)),E61) -> 0 | I61: =IFERROR(VLOOKUP(C61,'Clients List'!A:F,6,FALSE),"")
D62: =IFERROR(VLOOKUP(C62,'Clients List'!$A:$F,2,FALSE),"") | F62: =IF(OR(C62="",NOT(ISNUMBER(SEARCH("Package",D62)))),"",VLOOKUP(C62,'Clients List'!$A:$F,4,FALSE)-SUMIFS($E$2:$E62,$C$2:$C62,C62,$D$2:$D62,"*Package*")) | G62: =IF(ISNUMBER(SEARCH("Group",D62)),IFERROR("GRP-"&TEXT(IF(ISNUMBER(A62),A62,DATEVALUE(A62)),"yyyymmdd"),""),"" ) | H62: =IF(ISNUMBER(SEARCH("Group",D62)),IF(G62="",E62,IFERROR(E62/COUNTIF($G2:$G6000,G62),E62)),E62) -> 0 | I62: =IFERROR(VLOOKUP(C62,'Clients List'!A:F,6,FALSE),"")
D63: =IFERROR(VLOOKUP(C63,'Clients List'!$A:$F,2,FALSE),"") | F63: =IF(OR(C63="",NOT(ISNUMBER(SEARCH("Package",D63)))),"",VLOOKUP(C63,'Clients List'!$A:$F,4,FALSE)-SUMIFS($E$2:$E63,$C$2:$C63,C63,$D$2:$D63,"*Package*")) | G63: =IF(ISNUMBER(SEARCH("Group",D63)),IFERROR("GRP-"&TEXT(IF(ISNUMBER(A63),A63,DATEVALUE(A63)),"yyyymmdd"),""),"" ) | H63: =IF(ISNUMBER(SEARCH("Group",D63)),IF(G63="",E63,IFERROR(E63/COUNTIF($G2:$G6000,G63),E63)),E63) -> 0 | I63: =IFERROR(VLOOKUP(C63,'Clients List'!A:F,6,FALSE),"")
D64: =IFERROR(VLOOKUP(C64,'Clients List'!$A:$F,2,FALSE),"") | F64: =IF(OR(C64="",NOT(ISNUMBER(SEARCH("Package",D64)))),"",VLOOKUP(C64,'Clients List'!$A:$F,4,FALSE)-SUMIFS($E$2:$E64,$C$2:$C64,C64,$D$2:$D64,"*Package*")) | G64: =IF(ISNUMBER(SEARCH("Group",D64)),IFERROR("GRP-"&TEXT(IF(ISNUMBER(A64),A64,DATEVALUE(A64)),"yyyymmdd"),""),"" ) | H64: =IF(ISNUMBER(SEARCH("Group",D64)),IF(G64="",E64,IFERROR(E64/COUNTIF($G2:$G6000,G64),E64)),E64) -> 0 | I64: =IFERROR(VLOOKUP(C64,'Clients List'!A:F,6,FALSE),"")
D65: =IFERROR(VLOOKUP(C65,'Clients List'!$A:$F,2,FALSE),"") | F65: =IF(OR(C65="",NOT(ISNUMBER(SEARCH("Package",D65)))),"",VLOOKUP(C65,'Clients List'!$A:$F,4,FALSE)-SUMIFS($E$2:$E65,$C$2:$C65,C65,$D$2:$D65,"*Package*")) | G65: =IF(ISNUMBER(SEARCH("Group",D65)),IFERROR("GRP-"&TEXT(IF(ISNUMBER(A65),A65,DATEVALUE(A65)),"yyyymmdd"),""),"" ) | H65: =IF(ISNUMBER(SEARCH("Group",D65)),IF(G65="",E65,IFERROR(E65/COUNTIF($G2:$G6000,G65),E65)),E65) -> 0 | I65: =IFERROR(VLOOKUP(C65,'Clients List'!A:F,6,FALSE),"")
D66: =IFERROR(VLOOKUP(C66,'Clients List'!$A:$F,2,FALSE),"") | F66: =IF(OR(C66="",NOT(ISNUMBER(SEARCH("Package",D66)))),"",VLOOKUP(C66,'Clients List'!$A:$F,4,FALSE)-SUMIFS($E$2:$E66,$C$2:$C66,C66,$D$2:$D66,"*Package*")) | G66: =IF(ISNUMBER(SEARCH("Group",D66)),IFERROR("GRP-"&TEXT(IF(ISNUMBER(A66),A66,DATEVALUE(A66)),"yyyymmdd"),""),"" ) | H66: =IF(ISNUMBER(SEARCH("Group",D66)),IF(G66="",E66,IFERROR(E66/COUNTIF($G2:$G6000,G66),E66)),E66) -> 0 | I66: =IFERROR(VLOOKUP(C66,'Clients List'!A:F,6,FALSE),"")
D67: =IFERROR(VLOOKUP(C67,'Clients List'!$A:$F,2,FALSE),"") | F67: =IF(OR(C67="",NOT(ISNUMBER(SEARCH("Package",D67)))),"",VLOOKUP(C67,'Clients List'!$A:$F,4,FALSE)-SUMIFS($E$2:$E67,$C$2:$C67,C67,$D$2:$D67,"*Package*")) | G67: =IF(ISNUMBER(SEARCH("Group",D67)),IFERROR("GRP-"&TEXT(IF(ISNUMBER(A67),A67,DATEVALUE(A67)),"yyyymmdd"),""),"" ) | H67: =IF(ISNUMBER(SEARCH("Group",D67)),IF(G67="",E67,IFERROR(E67/COUNTIF($G2:$G6000,G67),E67)),E67) -> 0 | I67: =IFERROR(VLOOKUP(C67,'Clients List'!A:F,6,FALSE),"")
D68: =IFERROR(VLOOKUP(C68,'Clients List'!$A:$F,2,FALSE),"") | F68: =IF(OR(C68="",NOT(ISNUMBER(SEARCH("Package",D68)))),"",VLOOKUP(C68,'Clients List'!$A:$F,4,FALSE)-SUMIFS($E$2:$E68,$C$2:$C68,C68,$D$2:$D68,"*Package*")) | G68: =IF(ISNUMBER(SEARCH("Group",D68)),IFERROR("GRP-"&TEXT(IF(ISNUMBER(A68),A68,DATEVALUE(A68)),"yyyymmdd"),""),"" ) | H68: =IF(ISNUMBER(SEARCH("Group",D68)),IF(G68="",E68,IFERROR(E68/COUNTIF($G2:$G6000,G68),E68)),E68) -> 0 | I68: =IFERROR(VLOOKUP(C68,'Clients List'!A:F,6,FALSE),"")
D69: =IFERROR(VLOOKUP(C69,'Clients List'!$A:$F,2,FALSE),"") | F69: =IF(OR(C69="",NOT(ISNUMBER(SEARCH("Package",D69)))),"",VLOOKUP(C69,'Clients List'!$A:$F,4,FALSE)-SUMIFS($E$2:$E69,$C$2:$C69,C69,$D$2:$D69,"*Package*")) | G69: =IF(ISNUMBER(SEARCH("Group",D69)),IFERROR("GRP-"&TEXT(IF(ISNUMBER(A69),A69,DATEVALUE(A69)),"yyyymmdd"),""),"" ) | H69: =IF(ISNUMBER(SEARCH("Group",D69)),IF(G69="",E69,IFERROR(E69/COUNTIF($G2:$G6000,G69),E69)),E69) -> 0 | I69: =IFERROR(VLOOKUP(C69,'Clients List'!A:F,6,FALSE),"")
D70: =IFERROR(VLOOKUP(C70,'Clients List'!$A:$F,2,FALSE),"") | F70: =IF(OR(C70="",NOT(ISNUMBER(SEARCH("Package",D70)))),"",VLOOKUP(C70,'Clients List'!$A:$F,4,FALSE)-SUMIFS($E$2:$E70,$C$2:$C70,C70,$D$2:$D70,"*Package*")) | G70: =IF(ISNUMBER(SEARCH("Group",D70)),IFERROR("GRP-"&TEXT(IF(ISNUMBER(A70),A70,DATEVALUE(A70)),"yyyymmdd"),""),"" ) | H70: =IF(ISNUMBER(SEARCH("Group",D70)),IF(G70="",E70,IFERROR(E70/COUNTIF($G2:$G6000,G70),E70)),E70) -> 0 | I70: =IFERROR(VLOOKUP(C70,'Clients List'!A:F,6,FALSE),"")
D71: =IFERROR(VLOOKUP(C71,'Clients List'!$A:$F,2,FALSE),"") | F71: =IF(OR(C71="",NOT(ISNUMBER(SEARCH("Package",D71)))),"",VLOOKUP(C71,'Clients List'!$A:$F,4,FALSE)-SUMIFS($E$2:$E71,$C$2:$C71,C71,$D$2:$D71,"*Package*")) | G71: =IF(ISNUMBER(SEARCH("Group",D71)),IFERROR("GRP-"&TEXT(IF(ISNUMBER(A71),A71,DATEVALUE(A71)),"yyyymmdd"),""),"" ) | H71: =IF(ISNUMBER(SEARCH("Group",D71)),IF(G71="",E71,IFERROR(E71/COUNTIF($G2:$G6000,G71),E71)),E71) -> 0 | I71: =IFERROR(VLOOKUP(C71,'Clients List'!A:F,6,FALSE),"")
D72: =IFERROR(VLOOKUP(C72,'Clients List'!$A:$F,2,FALSE),"") | F72: =IF(OR(C72="",NOT(ISNUMBER(SEARCH("Package",D72)))),"",VLOOKUP(C72,'Clients List'!$A:$F,4,FALSE)-SUMIFS($E$2:$E72,$C$2:$C72,C72,$D$2:$D72,"*Package*")) | G72: =IF(ISNUMBER(SEARCH("Group",D72)),IFERROR("GRP-"&TEXT(IF(ISNUMBER(A72),A72,DATEVALUE(A72)),"yyyymmdd"),""),"" ) | H72: =IF(ISNUMBER(SEARCH("Group",D72)),IF(G72="",E72,IFERROR(E72/COUNTIF($G2:$G6000,G72),E72)),E72) -> 0 | I72: =IFERROR(VLOOKUP(C72,'Clients List'!A:F,6,FALSE),"")
D73: =IFERROR(VLOOKUP(C73,'Clients List'!$A:$F,2,FALSE),"") | F73: =IF(OR(C73="",NOT(ISNUMBER(SEARCH("Package",D73)))),"",VLOOKUP(C73,'Clients List'!$A:$F,4,FALSE)-SUMIFS($E$2:$E73,$C$2:$C73,C73,$D$2:$D73,"*Package*")) | G73: =IF(ISNUMBER(SEARCH("Group",D73)),IFERROR("GRP-"&TEXT(IF(ISNUMBER(A73),A73,DATEVALUE(A73)),"yyyymmdd"),""),"" ) | H73: =IF(ISNUMBER(SEARCH("Group",D73)),IF(G73="",E73,IFERROR(E73/COUNTIF($G2:$G6000,G73),E73)),E73) -> 0 | I73: =IFERROR(VLOOKUP(C73,'Clients List'!A:F,6,FALSE),"")
D74: =IFERROR(VLOOKUP(C74,'Clients List'!$A:$F,2,FALSE),"") | F74: =IF(OR(C74="",NOT(ISNUMBER(SEARCH("Package",D74)))),"",VLOOKUP(C74,'Clients List'!$A:$F,4,FALSE)-SUMIFS($E$2:$E74,$C$2:$C74,C74,$D$2:$D74,"*Package*")) | G74: =IF(ISNUMBER(SEARCH("Group",D74)),IFERROR("GRP-"&TEXT(IF(ISNUMBER(A74),A74,DATEVALUE(A74)),"yyyymmdd"),""),"" ) | H74: =IF(ISNUMBER(SEARCH("Group",D74)),IF(G74="",E74,IFERROR(E74/COUNTIF($G2:$G6000,G74),E74)),E74) -> 0 | I74: =IFERROR(VLOOKUP(C74,'Clients List'!A:F,6,FALSE),"")
D75: =IFERROR(VLOOKUP(C75,'Clients List'!$A:$F,2,FALSE),"") | F75: =IF(OR(C75="",NOT(ISNUMBER(SEARCH("Package",D75)))),"",VLOOKUP(C75,'Clients List'!$A:$F,4,FALSE)-SUMIFS($E$2:$E75,$C$2:$C75,C75,$D$2:$D75,"*Package*")) | G75: =IF(ISNUMBER(SEARCH("Group",D75)),IFERROR("GRP-"&TEXT(IF(ISNUMBER(A75),A75,DATEVALUE(A75)),"yyyymmdd"),""),"" ) | H75: =IF(ISNUMBER(SEARCH("Group",D75)),IF(G75="",E75,IFERROR(E75/COUNTIF($G2:$G6000,G75),E75)),E75) -> 0 | I75: =IFERROR(VLOOKUP(C75,'Clients List'!A:F,6,FALSE),"")
D76: =IFERROR(VLOOKUP(C76,'Clients List'!$A:$F,2,FALSE),"") | F76: =IF(OR(C76="",NOT(ISNUMBER(SEARCH("Package",D76)))),"",VLOOKUP(C76,'Clients List'!$A:$F,4,FALSE)-SUMIFS($E$2:$E76,$C$2:$C76,C76,$D$2:$D76,"*Package*")) | G76: =IF(ISNUMBER(SEARCH("Group",D76)),IFERROR("GRP-"&TEXT(IF(ISNUMBER(A76),A76,DATEVALUE(A76)),"yyyymmdd"),""),"" ) | H76: =IF(ISNUMBER(SEARCH("Group",D76)),IF(G76="",E76,IFERROR(E76/COUNTIF($G2:$G6000,G76),E76)),E76) -> 0 | I76: =IFERROR(VLOOKUP(C76,'Clients List'!A:F,6,FALSE),"")
D77: =IFERROR(VLOOKUP(C77,'Clients List'!$A:$F,2,FALSE),"") | F77: =IF(OR(C77="",NOT(ISNUMBER(SEARCH("Package",D77)))),"",VLOOKUP(C77,'Clients List'!$A:$F,4,FALSE)-SUMIFS($E$2:$E77,$C$2:$C77,C77,$D$2:$D77,"*Package*")) | G77: =IF(ISNUMBER(SEARCH("Group",D77)),IFERROR("GRP-"&TEXT(IF(ISNUMBER(A77),A77,DATEVALUE(A77)),"yyyymmdd"),""),"" ) | H77: =IF(ISNUMBER(SEARCH("Group",D77)),IF(G77="",E77,IFERROR(E77/COUNTIF($G2:$G6000,G77),E77)),E77) -> 0 | I77: =IFERROR(VLOOKUP(C77,'Clients List'!A:F,6,FALSE),"")
D78: =IFERROR(VLOOKUP(C78,'Clients List'!$A:$F,2,FALSE),"") | F78: =IF(OR(C78="",NOT(ISNUMBER(SEARCH("Package",D78)))),"",VLOOKUP(C78,'Clients List'!$A:$F,4,FALSE)-SUMIFS($E$2:$E78,$C$2:$C78,C78,$D$2:$D78,"*Package*")) | G78: =IF(ISNUMBER(SEARCH("Group",D78)),IFERROR("GRP-"&TEXT(IF(ISNUMBER(A78),A78,DATEVALUE(A78)),"yyyymmdd"),""),"" ) | H78: =IF(ISNUMBER(SEARCH("Group",D78)),IF(G78="",E78,IFERROR(E78/COUNTIF($G2:$G6000,G78),E78)),E78) -> 0 | I78: =IFERROR(VLOOKUP(C78,'Clients List'!A:F,6,FALSE),"")
D79: =IFERROR(VLOOKUP(C79,'Clients List'!$A:$F,2,FALSE),"") | F79: =IF(OR(C79="",NOT(ISNUMBER(SEARCH("Package",D79)))),"",VLOOKUP(C79,'Clients List'!$A:$F,4,FALSE)-SUMIFS($E$2:$E79,$C$2:$C79,C79,$D$2:$D79,"*Package*")) | G79: =IF(ISNUMBER(SEARCH("Group",D79)),IFERROR("GRP-"&TEXT(IF(ISNUMBER(A79),A79,DATEVALUE(A79)),"yyyymmdd"),""),"" ) | H79: =IF(ISNUMBER(SEARCH("Group",D79)),IF(G79="",E79,IFERROR(E79/COUNTIF($G2:$G6000,G79),E79)),E79) -> 0 | I79: =IFERROR(VLOOKUP(C79,'Clients List'!A:F,6,FALSE),"")
D80: =IFERROR(VLOOKUP(C80,'Clients List'!$A:$F,2,FALSE),"") | F80: =IF(OR(C80="",NOT(ISNUMBER(SEARCH("Package",D80)))),"",VLOOKUP(C80,'Clients List'!$A:$F,4,FALSE)-SUMIFS($E$2:$E80,$C$2:$C80,C80,$D$2:$D80,"*Package*")) | G80: =IF(ISNUMBER(SEARCH("Group",D80)),IFERROR("GRP-"&TEXT(IF(ISNUMBER(A80),A80,DATEVALUE(A80)),"yyyymmdd"),""),"" ) | H80: =IF(ISNUMBER(SEARCH("Group",D80)),IF(G80="",E80,IFERROR(E80/COUNTIF($G2:$G6000,G80),E80)),E80) -> 0 | I80: =IFERROR(VLOOKUP(C80,'Clients List'!A:F,6,FALSE),"")
D81: =IFERROR(VLOOKUP(C81,'Clients List'!$A:$F,2,FALSE),"") | F81: =IF(OR(C81="",NOT(ISNUMBER(SEARCH("Package",D81)))),"",VLOOKUP(C81,'Clients List'!$A:$F,4,FALSE)-SUMIFS($E$2:$E81,$C$2:$C81,C81,$D$2:$D81,"*Package*")) | G81: =IF(ISNUMBER(SEARCH("Group",D81)),IFERROR("GRP-"&TEXT(IF(ISNUMBER(A81),A81,DATEVALUE(A81)),"yyyymmdd"),""),"" ) | H81: =IF(ISNUMBER(SEARCH("Group",D81)),IF(G81="",E81,IFERROR(E81/COUNTIF($G2:$G6000,G81),E81)),E81) -> 0 | I81: =IFERROR(VLOOKUP(C81,'Clients List'!A:F,6,FALSE),"")
D82: =IFERROR(VLOOKUP(C82,'Clients List'!$A:$F,2,FALSE),"") | F82: =IF(OR(C82="",NOT(ISNUMBER(SEARCH("Package",D82)))),"",VLOOKUP(C82,'Clients List'!$A:$F,4,FALSE)-SUMIFS($E$2:$E82,$C$2:$C82,C82,$D$2:$D82,"*Package*")) | G82: =IF(ISNUMBER(SEARCH("Group",D82)),IFERROR("GRP-"&TEXT(IF(ISNUMBER(A82),A82,DATEVALUE(A82)),"yyyymmdd"),""),"" ) | H82: =IF(ISNUMBER(SEARCH("Group",D82)),IF(G82="",E82,IFERROR(E82/COUNTIF($G2:$G6000,G82),E82)),E82) -> 0 | I82: =IFERROR(VLOOKUP(C82,'Clients List'!A:F,6,FALSE),"")
D83: =IFERROR(VLOOKUP(C83,'Clients List'!$A:$F,2,FALSE),"") | F83: =IF(OR(C83="",NOT(ISNUMBER(SEARCH("Package",D83)))),"",VLOOKUP(C83,'Clients List'!$A:$F,4,FALSE)-SUMIFS($E$2:$E83,$C$2:$C83,C83,$D$2:$D83,"*Package*")) | G83: =IF(ISNUMBER(SEARCH("Group",D83)),IFERROR("GRP-"&TEXT(IF(ISNUMBER(A83),A83,DATEVALUE(A83)),"yyyymmdd"),""),"" ) | H83: =IF(ISNUMBER(SEARCH("Group",D83)),IF(G83="",E83,IFERROR(E83/COUNTIF($G2:$G6000,G83),E83)),E83) -> 0 | I83: =IFERROR(VLOOKUP(C83,'Clients List'!A:F,6,FALSE),"")
D84: =IFERROR(VLOOKUP(C84,'Clients List'!$A:$F,2,FALSE),"") | F84: =IF(OR(C84="",NOT(ISNUMBER(SEARCH("Package",D84)))),"",VLOOKUP(C84,'Clients List'!$A:$F,4,FALSE)-SUMIFS($E$2:$E84,$C$2:$C84,C84,$D$2:$D84,"*Package*")) | G84: =IF(ISNUMBER(SEARCH("Group",D84)),IFERROR("GRP-"&TEXT(IF(ISNUMBER(A84),A84,DATEVALUE(A84)),"yyyymmdd"),""),"" ) | H84: =IF(ISNUMBER(SEARCH("Group",D84)),IF(G84="",E84,IFERROR(E84/COUNTIF($G2:$G6000,G84),E84)),E84) -> 0 | I84: =IFERROR(VLOOKUP(C84,'Clients List'!A:F,6,FALSE),"")
D85: =IFERROR(VLOOKUP(C85,'Clients List'!$A:$F,2,FALSE),"") | F85: =IF(OR(C85="",NOT(ISNUMBER(SEARCH("Package",D85)))),"",VLOOKUP(C85,'Clients List'!$A:$F,4,FALSE)-SUMIFS($E$2:$E85,$C$2:$C85,C85,$D$2:$D85,"*Package*")) | G85: =IF(ISNUMBER(SEARCH("Group",D85)),IFERROR("GRP-"&TEXT(IF(ISNUMBER(A85),A85,DATEVALUE(A85)),"yyyymmdd"),""),"" ) | H85: =IF(ISNUMBER(SEARCH("Group",D85)),IF(G85="",E85,IFERROR(E85/COUNTIF($G2:$G6000,G85),E85)),E85) -> 0 | I85: =IFERROR(VLOOKUP(C85,'Clients List'!A:F,6,FALSE),"")
D86: =IFERROR(VLOOKUP(C86,'Clients List'!$A:$F,2,FALSE),"") | F86: =IF(OR(C86="",NOT(ISNUMBER(SEARCH("Package",D86)))),"",VLOOKUP(C86,'Clients List'!$A:$F,4,FALSE)-SUMIFS($E$2:$E86,$C$2:$C86,C86,$D$2:$D86,"*Package*")) | G86: =IF(ISNUMBER(SEARCH("Group",D86)),IFERROR("GRP-"&TEXT(IF(ISNUMBER(A86),A86,DATEVALUE(A86)),"yyyymmdd"),""),"" ) | H86: =IF(ISNUMBER(SEARCH("Group",D86)),IF(G86="",E86,IFERROR(E86/COUNTIF($G2:$G6000,G86),E86)),E86) -> 0 | I86: =IFERROR(VLOOKUP(C86,'Clients List'!A:F,6,FALSE),"")
D87: =IFERROR(VLOOKUP(C87,'Clients List'!$A:$F,2,FALSE),"") | F87: =IF(OR(C87="",NOT(ISNUMBER(SEARCH("Package",D87)))),"",VLOOKUP(C87,'Clients List'!$A:$F,4,FALSE)-SUMIFS($E$2:$E87,$C$2:$C87,C87,$D$2:$D87,"*Package*")) | G87: =IF(ISNUMBER(SEARCH("Group",D87)),IFERROR("GRP-"&TEXT(IF(ISNUMBER(A87),A87,DATEVALUE(A87)),"yyyymmdd"),""),"" ) | H87: =IF(ISNUMBER(SEARCH("Group",D87)),IF(G87="",E87,IFERROR(E87/COUNTIF($G2:$G6000,G87),E87)),E87) -> 0 | I87: =IFERROR(VLOOKUP(C87,'Clients List'!A:F,6,FALSE),"")
D88: =IFERROR(VLOOKUP(C88,'Clients List'!$A:$F,2,FALSE),"") | F88: =IF(OR(C88="",NOT(ISNUMBER(SEARCH("Package",D88)))),"",VLOOKUP(C88,'Clients List'!$A:$F,4,FALSE)-SUMIFS($E$2:$E88,$C$2:$C88,C88,$D$2:$D88,"*Package*")) | G88: =IF(ISNUMBER(SEARCH("Group",D88)),IFERROR("GRP-"&TEXT(IF(ISNUMBER(A88),A88,DATEVALUE(A88)),"yyyymmdd"),""),"" ) | H88: =IF(ISNUMBER(SEARCH("Group",D88)),IF(G88="",E88,IFERROR(E88/COUNTIF($G2:$G6000,G88),E88)),E88) -> 0 | I88: =IFERROR(VLOOKUP(C88,'Clients List'!A:F,6,FALSE),"")
D89: =IFERROR(VLOOKUP(C89,'Clients List'!$A:$F,2,FALSE),"") | F89: =IF(OR(C89="",NOT(ISNUMBER(SEARCH("Package",D89)))),"",VLOOKUP(C89,'Clients List'!$A:$F,4,FALSE)-SUMIFS($E$2:$E89,$C$2:$C89,C89,$D$2:$D89,"*Package*")) | G89: =IF(ISNUMBER(SEARCH("Group",D89)),IFERROR("GRP-"&TEXT(IF(ISNUMBER(A89),A89,DATEVALUE(A89)),"yyyymmdd"),""),"" ) | H89: =IF(ISNUMBER(SEARCH("Group",D89)),IF(G89="",E89,IFERROR(E89/COUNTIF($G2:$G6000,G89),E89)),E89) -> 0 | I89: =IFERROR(VLOOKUP(C89,'Clients List'!A:F,6,FALSE),"")
D90: =IFERROR(VLOOKUP(C90,'Clients List'!$A:$F,2,FALSE),"") | F90: =IF(OR(C90="",NOT(ISNUMBER(SEARCH("Package",D90)))),"",VLOOKUP(C90,'Clients List'!$A:$F,4,FALSE)-SUMIFS($E$2:$E90,$C$2:$C90,C90,$D$2:$D90,"*Package*")) | G90: =IF(ISNUMBER(SEARCH("Group",D90)),IFERROR("GRP-"&TEXT(IF(ISNUMBER(A90),A90,DATEVALUE(A90)),"yyyymmdd"),""),"" ) | H90: =IF(ISNUMBER(SEARCH("Group",D90)),IF(G90="",E90,IFERROR(E90/COUNTIF($G2:$G6000,G90),E90)),E90) -> 0 | I90: =IFERROR(VLOOKUP(C90,'Clients List'!A:F,6,FALSE),"")
D91: =IFERROR(VLOOKUP(C91,'Clients List'!$A:$F,2,FALSE),"") | F91: =IF(OR(C91="",NOT(ISNUMBER(SEARCH("Package",D91)))),"",VLOOKUP(C91,'Clients List'!$A:$F,4,FALSE)-SUMIFS($E$2:$E91,$C$2:$C91,C91,$D$2:$D91,"*Package*")) | G91: =IF(ISNUMBER(SEARCH("Group",D91)),IFERROR("GRP-"&TEXT(IF(ISNUMBER(A91),A91,DATEVALUE(A91)),"yyyymmdd"),""),"" ) | H91: =IF(ISNUMBER(SEARCH("Group",D91)),IF(G91="",E91,IFERROR(E91/COUNTIF($G2:$G6000,G91),E91)),E91) -> 0 | I91: =IFERROR(VLOOKUP(C91,'Clients List'!A:F,6,FALSE),"")
D92: =IFERROR(VLOOKUP(C92,'Clients List'!$A:$F,2,FALSE),"") | F92: =IF(OR(C92="",NOT(ISNUMBER(SEARCH("Package",D92)))),"",VLOOKUP(C92,'Clients List'!$A:$F,4,FALSE)-SUMIFS($E$2:$E92,$C$2:$C92,C92,$D$2:$D92,"*Package*")) | G92: =IF(ISNUMBER(SEARCH("Group",D92)),IFERROR("GRP-"&TEXT(IF(ISNUMBER(A92),A92,DATEVALUE(A92)),"yyyymmdd"),""),"" ) | H92: =IF(ISNUMBER(SEARCH("Group",D92)),IF(G92="",E92,IFERROR(E92/COUNTIF($G2:$G6000,G92),E92)),E92) -> 0 | I92: =IFERROR(VLOOKUP(C92,'Clients List'!A:F,6,FALSE),"")
D93: =IFERROR(VLOOKUP(C93,'Clients List'!$A:$F,2,FALSE),"") | F93: =IF(OR(C93="",NOT(ISNUMBER(SEARCH("Package",D93)))),"",VLOOKUP(C93,'Clients List'!$A:$F,4,FALSE)-SUMIFS($E$2:$E93,$C$2:$C93,C93,$D$2:$D93,"*Package*")) | G93: =IF(ISNUMBER(SEARCH("Group",D93)),IFERROR("GRP-"&TEXT(IF(ISNUMBER(A93),A93,DATEVALUE(A93)),"yyyymmdd"),""),"" ) | H93: =IF(ISNUMBER(SEARCH("Group",D93)),IF(G93="",E93,IFERROR(E93/COUNTIF($G2:$G6000,G93),E93)),E93) -> 0 | I93: =IFERROR(VLOOKUP(C93,'Clients List'!A:F,6,FALSE),"")
D94: =IFERROR(VLOOKUP(C94,'Clients List'!$A:$F,2,FALSE),"") | F94: =IF(OR(C94="",NOT(ISNUMBER(SEARCH("Package",D94)))),"",VLOOKUP(C94,'Clients List'!$A:$F,4,FALSE)-SUMIFS($E$2:$E94,$C$2:$C94,C94,$D$2:$D94,"*Package*")) | G94: =IF(ISNUMBER(SEARCH("Group",D94)),IFERROR("GRP-"&TEXT(IF(ISNUMBER(A94),A94,DATEVALUE(A94)),"yyyymmdd"),""),"" ) | H94: =IF(ISNUMBER(SEARCH("Group",D94)),IF(G94="",E94,IFERROR(E94/COUNTIF($G2:$G6000,G94),E94)),E94) -> 0 | I94: =IFERROR(VLOOKUP(C94,'Clients List'!A:F,6,FALSE),"")
D95: =IFERROR(VLOOKUP(C95,'Clients List'!$A:$F,2,FALSE),"") | F95: =IF(OR(C95="",NOT(ISNUMBER(SEARCH("Package",D95)))),"",VLOOKUP(C95,'Clients List'!$A:$F,4,FALSE)-SUMIFS($E$2:$E95,$C$2:$C95,C95,$D$2:$D95,"*Package*")) | G95: =IF(ISNUMBER(SEARCH("Group",D95)),IFERROR("GRP-"&TEXT(IF(ISNUMBER(A95),A95,DATEVALUE(A95)),"yyyymmdd"),""),"" ) | H95: =IF(ISNUMBER(SEARCH("Group",D95)),IF(G95="",E95,IFERROR(E95/COUNTIF($G2:$G6000,G95),E95)),E95) -> 0 | I95: =IFERROR(VLOOKUP(C95,'Clients List'!A:F,6,FALSE),"")
D96: =IFERROR(VLOOKUP(C96,'Clients List'!$A:$F,2,FALSE),"") | F96: =IF(OR(C96="",NOT(ISNUMBER(SEARCH("Package",D96)))),"",VLOOKUP(C96,'Clients List'!$A:$F,4,FALSE)-SUMIFS($E$2:$E96,$C$2:$C96,C96,$D$2:$D96,"*Package*")) | G96: =IF(ISNUMBER(SEARCH("Group",D96)),IFERROR("GRP-"&TEXT(IF(ISNUMBER(A96),A96,DATEVALUE(A96)),"yyyymmdd"),""),"" ) | H96: =IF(ISNUMBER(SEARCH("Group",D96)),IF(G96="",E96,IFERROR(E96/COUNTIF($G2:$G6000,G96),E96)),E96) -> 0 | I96: =IFERROR(VLOOKUP(C96,'Clients List'!A:F,6,FALSE),"")
D97: =IFERROR(VLOOKUP(C97,'Clients List'!$A:$F,2,FALSE),"") | F97: =IF(OR(C97="",NOT(ISNUMBER(SEARCH("Package",D97)))),"",VLOOKUP(C97,'Clients List'!$A:$F,4,FALSE)-SUMIFS($E$2:$E97,$C$2:$C97,C97,$D$2:$D97,"*Package*")) | G97: =IF(ISNUMBER(SEARCH("Group",D97)),IFERROR("GRP-"&TEXT(IF(ISNUMBER(A97),A97,DATEVALUE(A97)),"yyyymmdd"),""),"" ) | H97: =IF(ISNUMBER(SEARCH("Group",D97)),IF(G97="",E97,IFERROR(E97/COUNTIF($G2:$G6000,G97),E97)),E97) -> 0 | I97: =IFERROR(VLOOKUP(C97,'Clients List'!A:F,6,FALSE),"")
D98: =IFERROR(VLOOKUP(C98,'Clients List'!$A:$F,2,FALSE),"") | F98: =IF(OR(C98="",NOT(ISNUMBER(SEARCH("Package",D98)))),"",VLOOKUP(C98,'Clients List'!$A:$F,4,FALSE)-SUMIFS($E$2:$E98,$C$2:$C98,C98,$D$2:$D98,"*Package*")) | G98: =IF(ISNUMBER(SEARCH("Group",D98)),IFERROR("GRP-"&TEXT(IF(ISNUMBER(A98),A98,DATEVALUE(A98)),"yyyymmdd"),""),"" ) | H98: =IF(ISNUMBER(SEARCH("Group",D98)),IF(G98="",E98,IFERROR(E98/COUNTIF($G2:$G6000,G98),E98)),E98) -> 0 | I98: =IFERROR(VLOOKUP(C98,'Clients List'!A:F,6,FALSE),"")
D99: =IFERROR(VLOOKUP(C99,'Clients List'!$A:$F,2,FALSE),"") | F99: =IF(OR(C99="",NOT(ISNUMBER(SEARCH("Package",D99)))),"",VLOOKUP(C99,'Clients List'!$A:$F,4,FALSE)-SUMIFS($E$2:$E99,$C$2:$C99,C99,$D$2:$D99,"*Package*")) | G99: =IF(ISNUMBER(SEARCH("Group",D99)),IFERROR("GRP-"&TEXT(IF(ISNUMBER(A99),A99,DATEVALUE(A99)),"yyyymmdd"),""),"" ) | H99: =IF(ISNUMBER(SEARCH("Group",D99)),IF(G99="",E99,IFERROR(E99/COUNTIF($G2:$G6000,G99),E99)),E99) -> 0 | I99: =IFERROR(VLOOKUP(C99,'Clients List'!A:F,6,FALSE),"")
D100: =IFERROR(VLOOKUP(C100,'Clients List'!$A:$F,2,FALSE),"") | F100: =IF(OR(C100="",NOT(ISNUMBER(SEARCH("Package",D100)))),"",VLOOKUP(C100,'Clients List'!$A:$F,4,FALSE)-SUMIFS($E$2:$E100,$C$2:$C100,C100,$D$2:$D100,"*Package*")) | G100: =IF(ISNUMBER(SEARCH("Group",D100)),IFERROR("GRP-"&TEXT(IF(ISNUMBER(A100),A100,DATEVALUE(A100)),"yyyymmdd"),""),"" ) | H100: =IF(ISNUMBER(SEARCH("Group",D100)),IF(G100="",E100,IFERROR(E100/COUNTIF($G2:$G6000,G100),E100)),E100) -> 0 | I100: =IFERROR(VLOOKUP(C100,'Clients List'!A:F,6,FALSE),"")
...

Sheet Revenue
A1: Revenue (Lesson Hours × Client Default Price) – 2026
A3: Month | B3: Total Lesson Hours | C3: Calculated Revenue | D3: Expances | E3: Net Profit
A4: January 2026 | B4: =SUMPRODUCT(--ISNUMBER('Lessons Log'!$A$2:$A$6000),--(YEAR('Lessons Log'!$A$2:$A$6000)=2026),--(MONTH('Lessons Log'!$A$2:$A$6000)=1),'Lessons Log'!$H$2:$H$6000) -> 0 | C4: =SUMPRODUCT(--ISNUMBER('Lessons Log'!$A$2:$A$6000),--(YEAR('Lessons Log'!$A$2:$A$6000)=2026),--(MONTH('Lessons Log'!$A$2:$A$6000)=1),'Lessons Log'!$E$2:$E$6000,'Lessons Log'!$I$2:$I$6000) -> 0
A5: February 2026 | B5: =SUMPRODUCT(--ISNUMBER('Lessons Log'!$A$2:$A$6000),--(YEAR('Lessons Log'!$A$2:$A$6000)=2026),--(MONTH('Lessons Log'!$A$2:$A$6000)=2),'Lessons Log'!$H$2:$H$6000) -> 0 | C5: =SUMPRODUCT(--ISNUMBER('Lessons Log'!$A$2:$A$6000),--(YEAR('Lessons Log'!$A$2:$A$6000)=2026),--(MONTH('Lessons Log'!$A$2:$A$6000)=2),'Lessons Log'!$E$2:$E$6000,'Lessons Log'!$I$2:$I$6000) -> 0
A6: March 2026 | B6: =SUMPRODUCT(--ISNUMBER('Lessons Log'!$A$2:$A$6000),--(YEAR('Lessons Log'!$A$2:$A$6000)=2026),--(MONTH('Lessons Log'!$A$2:$A$6000)=3),'Lessons Log'!$H$2:$H$6000) -> 0 | C6: =SUMPRODUCT(--ISNUMBER('Lessons Log'!$A$2:$A$6000),--(YEAR('Lessons Log'!$A$2:$A$6000)=2026),--(MONTH('Lessons Log'!$A$2:$A$6000)=3),'Lessons Log'!$E$2:$E$6000,'Lessons Log'!$I$2:$I$6000) -> 0
A7: April 2026 | B7: =SUMPRODUCT(--ISNUMBER('Lessons Log'!$A$2:$A$6000),--(YEAR('Lessons Log'!$A$2:$A$6000)=2026),--(MONTH('Lessons Log'!$A$2:$A$6000)=4),'Lessons Log'!$H$2:$H$6000) -> 0 | C7: =SUMPRODUCT(--ISNUMBER('Lessons Log'!$A$2:$A$6000),--(YEAR('Lessons Log'!$A$2:$A$6000)=2026),--(MONTH('Lessons Log'!$A$2:$A$6000)=4),'Lessons Log'!$E$2:$E$6000,'Lessons Log'!$I$2:$I$6000) -> 0
A8: May 2026 | B8: =SUMPRODUCT(--ISNUMBER('Lessons Log'!$A$2:$A$6000),--(YEAR('Lessons Log'!$A$2:$A$6000)=2026),--(MONTH('Lessons Log'!$A$2:$A$6000)=5),'Lessons Log'!$H$2:$H$6000) -> 0 | C8: =SUMPRODUCT(--ISNUMBER('Lessons Log'!$A$2:$A$6000),--(YEAR('Lessons Log'!$A$2:$A$6000)=2026),--(MONTH('Lessons Log'!$A$2:$A$6000)=5),'Lessons Log'!$E$2:$E$6000,'Lessons Log'!$I$2:$I$6000) -> 0
A9: June 2026 | B9: =SUMPRODUCT(--ISNUMBER('Lessons Log'!$A$2:$A$6000),--(YEAR('Lessons Log'!$A$2:$A$6000)=2026),--(MONTH('Lessons Log'!$A$2:$A$6000)=6),'Lessons Log'!$H$2:$H$6000) -> 0 | C9: =SUMPRODUCT(--ISNUMBER('Lessons Log'!$A$2:$A$6000),--(YEAR('Lessons Log'!$A$2:$A$6000)=2026),--(MONTH('Lessons Log'!$A$2:$A$6000)=6),'Lessons Log'!$E$2:$E$6000,'Lessons Log'!$I$2:$I$6000) -> 0
A10: July 2026 | B10: =SUMPRODUCT(--ISNUMBER('Lessons Log'!$A$2:$A$6000),--(YEAR('Lessons Log'!$A$2:$A$6000)=2026),--(MONTH('Lessons Log'!$A$2:$A$6000)=7),'Lessons Log'!$H$2:$H$6000) -> 0 | C10: =SUMPRODUCT(--ISNUMBER('Lessons Log'!$A$2:$A$6000),--(YEAR('Lessons Log'!$A$2:$A$6000)=2026),--(MONTH('Lessons Log'!$A$2:$A$6000)=7),'Lessons Log'!$E$2:$E$6000,'Lessons Log'!$I$2:$I$6000) -> 0
A11: August 2026 | B11: =SUMPRODUCT(--ISNUMBER('Lessons Log'!$A$2:$A$6000),--(YEAR('Lessons Log'!$A$2:$A$6000)=2026),--(MONTH('Lessons Log'!$A$2:$A$6000)=8),'Lessons Log'!$H$2:$H$6000) -> 0 | C11: =SUMPRODUCT(--ISNUMBER('Lessons Log'!$A$2:$A$6000),--(YEAR('Lessons Log'!$A$2:$A$6000)=2026),--(MONTH('Lessons Log'!$A$2:$A$6000)=8),'Lessons Log'!$E$2:$E$6000,'Lessons Log'!$I$2:$I$6000) -> 0
A12: September 2026 | B12: =SUMPRODUCT(--ISNUMBER('Lessons Log'!$A$2:$A$6000),--(YEAR('Lessons Log'!$A$2:$A$6000)=2026),--(MONTH('Lessons Log'!$A$2:$A$6000)=9),'Lessons Log'!$H$2:$H$6000) -> 0 | C12: =SUMPRODUCT(--ISNUMBER('Lessons Log'!$A$2:$A$6000),--(YEAR('Lessons Log'!$A$2:$A$6000)=2026),--(MONTH('Lessons Log'!$A$2:$A$6000)=9),'Lessons Log'!$E$2:$E$6000,'Lessons Log'!$I$2:$I$6000) -> 0
A13: October 2026 | B13: =SUMPRODUCT(--ISNUMBER('Lessons Log'!$A$2:$A$6000),--(YEAR('Lessons Log'!$A$2:$A$6000)=2026),--(MONTH('Lessons Log'!$A$2:$A$6000)=10),'Lessons Log'!$H$2:$H$6000) -> 0 | C13: =SUMPRODUCT(--ISNUMBER('Lessons Log'!$A$2:$A$6000),--(YEAR('Lessons Log'!$A$2:$A$6000)=2026),--(MONTH('Lessons Log'!$A$2:$A$6000)=10),'Lessons Log'!$E$2:$E$6000,'Lessons Log'!$I$2:$I$6000) -> 0
A14: November 2026 | B14: =SUMPRODUCT(--ISNUMBER('Lessons Log'!$A$2:$A$6000),--(YEAR('Lessons Log'!$A$2:$A$6000)=2026),--(MONTH('Lessons Log'!$A$2:$A$6000)=11),'Lessons Log'!$H$2:$H$6000) -> 0 | C14: =SUMPRODUCT(--ISNUMBER('Lessons Log'!$A$2:$A$6000),--(YEAR('Lessons Log'!$A$2:$A$6000)=2026),--(MONTH('Lessons Log'!$A$2:$A$6000)=11),'Lessons Log'!$E$2:$E$6000,'Lessons Log'!$I$2:$I$6000) -> 0
A15: December 2026 | B15: =SUMPRODUCT(--ISNUMBER('Lessons Log'!$A$2:$A$6000),--(YEAR('Lessons Log'!$A$2:$A$6000)=2026),--(MONTH('Lessons Log'!$A$2:$A$6000)=12),'Lessons Log'!$H$2:$H$6000) -> 0 | C15: =SUMPRODUCT(--ISNUMBER('Lessons Log'!$A$2:$A$6000),--(YEAR('Lessons Log'!$A$2:$A$6000)=2026),--(MONTH('Lessons Log'!$A$2:$A$6000)=12),'Lessons Log'!$E$2:$E$6000,'Lessons Log'!$I$2:$I$6000) -> 0
A16: TOTAL 2026 | B16: =SUM(B4:B15) -> 0 | C16: =SUM(C4:C15) -> 0 | D16: =SUM(D4:D15) -> 0 | E16: =C16-D16 -> 0

Sheet ValidationLists
A1: Private Lesson $120
A2: Semi Lesson $140
A3: Group Lesson $50
A4: Package Private Lesson $110
A5: Package Semi Lesson $125
A6: Package Group Lesson $40
A7: Custom Private Lesson
A8: Custom Semi Lesson
A9: Custom Group Lesson
A10: Custom Package Private Lesson
A11: Custom Package Semi Lesson
A12: Custom Package Group Lesson
... A14: Custom Tennis Camp
